{"b4w_format_version": "6.03", "b4w_filepath_blend": "../Man4_Sax_Player2_JOIN_DOWN_sample_.blend", "actions": [{"name": "PoseLib", "uuid": "e7aafab5c3a0696f4c107edc5821a10f", "frame_range": [1, 2], "fcurves": {"pose.bones[\"wrist_R\"].location": {"0": {"bin_data_pos": [124660, 5], "last_frame_offset": 0, "num_channels": 8}, "1": {"bin_data_pos": [124665, 5], "last_frame_offset": 0, "num_channels": 8}, "2": {"bin_data_pos": [124670, 5], "last_frame_offset": 0, "num_channels": 8}}, "pose.bones[\"wrist_R\"].rotation_quaternion": {"0": {"bin_data_pos": [124675, 5], "last_frame_offset": 0, "num_channels": 8}, "1": {"bin_data_pos": [124680, 5], "last_frame_offset": 0, "num_channels": 8}, "2": {"bin_data_pos": [124685, 5], "last_frame_offset": 0, "num_channels": 8}, "3": {"bin_data_pos": [124690, 5], "last_frame_offset": 0, "num_channels": 8}}, "pose.bones[\"wrist_R\"].scale": {"0": {"bin_data_pos": [124695, 5], "last_frame_offset": 0, "num_channels": 8}}}}], "images": [{"name": "young_lightskinned_male_diffuse2.png.001", "uuid": "55240bbc433961e81e203e01b6cc124a", "filepath": "../textures/man4/textures/young_lightskinned_male_diffuse2.png", "size": [2048, 2048], "source": "FILE", "colorspace_settings_name": "sRGB"}, {"name": "shoes03_diffuse.png", "uuid": "b89f0dd43114eca0e091ba412b33d033", "filepath": "../textures/man4/textures/shoes03_diffuse.png", "size": [1024, 1024], "source": "FILE", "colorspace_settings_name": "sRGB"}, {"name": "male_casualsuit01_diffuse.png", "uuid": "141c79f78729c17a6f2dc28aef777e88", "filepath": "../textures/man4/textures/male_casualsuit01_diffuse.png", "size": [2048, 2048], "source": "FILE", "colorspace_settings_name": "sRGB"}, {"name": "teeth.png.001", "uuid": "346c932a6714298b349a3f6be33d5d5b", "filepath": "../textures/man4/textures/teeth.png", "size": [2048, 2048], "source": "FILE", "colorspace_settings_name": "sRGB"}, {"name": "eyebrow012.png", "uuid": "6d9d58ff412eb5e1a14fb6943c78c6e6", "filepath": "../textures/man4/textures/eyebrow012.png", "size": [512, 512], "source": "FILE", "colorspace_settings_name": "sRGB"}, {"name": "brown_eye.png.001", "uuid": "3bcac8cc9ab24c8a3a7b17aa6c2057e0", "filepath": "../textures/man4/textures/brown_eye.png", "size": [1024, 1024], "source": "FILE", "colorspace_settings_name": "sRGB"}, {"name": "short02_diffuse.png", "uuid": "f1e6976b5795d18a8e45fd0e4174724c", "filepath": "../textures/man4/textures/short02_diffuse.png", "size": [2048, 2048], "source": "FILE", "colorspace_settings_name": "sRGB"}], "textures": [{"name": "old_cauca_male", "uuid": "25bdad333d00a31d9017c0edfda94cdd", "type": "IMAGE", "b4w_source_type": "NONE", "b4w_source_id": "", "b4w_source_size": "128", "b4w_enable_canvas_mipmapping": true, "extension": "REPEAT", "b4w_use_map_parallax": false, "b4w_parallax_scale": 0.02, "b4w_parallax_steps": 5, "b4w_parallax_lod_dist": 5, "b4w_water_foam": false, "b4w_foam_uv_freq": [1, 1], "b4w_foam_uv_magnitude": [1, 1], "b4w_shore_dist_map": false, "b4w_anisotropic_filtering": "DEFAULT", "b4w_shore_boundings": [0, 0, 0, 0], "b4w_max_shore_dist": 100, "b4w_disable_compression": false, "b4w_use_as_skydome": true, "b4w_use_as_environment_lighting": false, "image": {"uuid": "55240bbc433961e81e203e01b6cc124a"}, "frame_duration": 0, "frame_offset": 0, "frame_start": 0, "use_auto_refresh": false, "use_cyclic": false, "movie_length": 0, "b4w_nla_video": false, "noise_intensity": null, "noise_scale": null, "use_color_ramp": false, "color_ramp": null}, {"name": "SHOES03", "uuid": "84a1fb4484b4e84346afe0cacc9da844", "type": "IMAGE", "b4w_source_type": "NONE", "b4w_source_id": "", "b4w_source_size": "128", "b4w_enable_canvas_mipmapping": true, "extension": "REPEAT", "b4w_use_map_parallax": false, "b4w_parallax_scale": 0.02, "b4w_parallax_steps": 5, "b4w_parallax_lod_dist": 5, "b4w_water_foam": false, "b4w_foam_uv_freq": [1, 1], "b4w_foam_uv_magnitude": [1, 1], "b4w_shore_dist_map": false, "b4w_anisotropic_filtering": "DEFAULT", "b4w_shore_boundings": [0, 0, 0, 0], "b4w_max_shore_dist": 100, "b4w_disable_compression": false, "b4w_use_as_skydome": true, "b4w_use_as_environment_lighting": false, "image": {"uuid": "b89f0dd43114eca0e091ba412b33d033"}, "frame_duration": 0, "frame_offset": 0, "frame_start": 0, "use_auto_refresh": false, "use_cyclic": false, "movie_length": 0, "b4w_nla_video": false, "noise_intensity": null, "noise_scale": null, "use_color_ramp": false, "color_ramp": null}, {"name": "MAN_CASUAL01", "uuid": "e3ebc15a047d097018b6b418bd9aa10c", "type": "IMAGE", "b4w_source_type": "NONE", "b4w_source_id": "", "b4w_source_size": "128", "b4w_enable_canvas_mipmapping": true, "extension": "REPEAT", "b4w_use_map_parallax": false, "b4w_parallax_scale": 0.02, "b4w_parallax_steps": 5, "b4w_parallax_lod_dist": 5, "b4w_water_foam": false, "b4w_foam_uv_freq": [1, 1], "b4w_foam_uv_magnitude": [1, 1], "b4w_shore_dist_map": false, "b4w_anisotropic_filtering": "DEFAULT", "b4w_shore_boundings": [0, 0, 0, 0], "b4w_max_shore_dist": 100, "b4w_disable_compression": false, "b4w_use_as_skydome": true, "b4w_use_as_environment_lighting": false, "image": {"uuid": "141c79f78729c17a6f2dc28aef777e88"}, "frame_duration": 0, "frame_offset": 0, "frame_start": 0, "use_auto_refresh": false, "use_cyclic": false, "movie_length": 0, "b4w_nla_video": false, "noise_intensity": null, "noise_scale": null, "use_color_ramp": false, "color_ramp": null}, {"name": "TEETH", "uuid": "b424db2696230583fd8aa11aeb99d506", "type": "IMAGE", "b4w_source_type": "NONE", "b4w_source_id": "", "b4w_source_size": "128", "b4w_enable_canvas_mipmapping": true, "extension": "REPEAT", "b4w_use_map_parallax": false, "b4w_parallax_scale": 0.02, "b4w_parallax_steps": 5, "b4w_parallax_lod_dist": 5, "b4w_water_foam": false, "b4w_foam_uv_freq": [1, 1], "b4w_foam_uv_magnitude": [1, 1], "b4w_shore_dist_map": false, "b4w_anisotropic_filtering": "DEFAULT", "b4w_shore_boundings": [0, 0, 0, 0], "b4w_max_shore_dist": 100, "b4w_disable_compression": false, "b4w_use_as_skydome": true, "b4w_use_as_environment_lighting": false, "image": {"uuid": "346c932a6714298b349a3f6be33d5d5b"}, "frame_duration": 0, "frame_offset": 0, "frame_start": 0, "use_auto_refresh": false, "use_cyclic": false, "movie_length": 0, "b4w_nla_video": false, "noise_intensity": null, "noise_scale": null, "use_color_ramp": false, "color_ramp": null}, {"name": "eyebrow012", "uuid": "fbec5bafed75899e5c33c86605973e5d", "type": "IMAGE", "b4w_source_type": "NONE", "b4w_source_id": "", "b4w_source_size": "128", "b4w_enable_canvas_mipmapping": true, "extension": "REPEAT", "b4w_use_map_parallax": false, "b4w_parallax_scale": 0.02, "b4w_parallax_steps": 5, "b4w_parallax_lod_dist": 5, "b4w_water_foam": false, "b4w_foam_uv_freq": [1, 1], "b4w_foam_uv_magnitude": [1, 1], "b4w_shore_dist_map": false, "b4w_anisotropic_filtering": "DEFAULT", "b4w_shore_boundings": [0, 0, 0, 0], "b4w_max_shore_dist": 100, "b4w_disable_compression": false, "b4w_use_as_skydome": true, "b4w_use_as_environment_lighting": false, "image": {"uuid": "6d9d58ff412eb5e1a14fb6943c78c6e6"}, "frame_duration": 0, "frame_offset": 0, "frame_start": 0, "use_auto_refresh": false, "use_cyclic": false, "movie_length": 0, "b4w_nla_video": false, "noise_intensity": null, "noise_scale": null, "use_color_ramp": false, "color_ramp": null}, {"name": "Texture.006", "uuid": "f0e6aba741649c10490fcd160043fd86", "type": "IMAGE", "b4w_source_type": "NONE", "b4w_source_id": "", "b4w_source_size": "128", "b4w_enable_canvas_mipmapping": true, "extension": "REPEAT", "b4w_use_map_parallax": false, "b4w_parallax_scale": 0.02, "b4w_parallax_steps": 5, "b4w_parallax_lod_dist": 5, "b4w_water_foam": false, "b4w_foam_uv_freq": [1, 1], "b4w_foam_uv_magnitude": [1, 1], "b4w_shore_dist_map": false, "b4w_anisotropic_filtering": "DEFAULT", "b4w_shore_boundings": [0, 0, 0, 0], "b4w_max_shore_dist": 100, "b4w_disable_compression": false, "b4w_use_as_skydome": true, "b4w_use_as_environment_lighting": false, "image": {"uuid": "3bcac8cc9ab24c8a3a7b17aa6c2057e0"}, "frame_duration": 0, "frame_offset": 0, "frame_start": 0, "use_auto_refresh": false, "use_cyclic": false, "movie_length": 0, "b4w_nla_video": false, "noise_intensity": null, "noise_scale": null, "use_color_ramp": false, "color_ramp": null}, {"name": "SHORT02", "uuid": "f9674c99eadbb1d85be80cee8ab7ea04", "type": "IMAGE", "b4w_source_type": "NONE", "b4w_source_id": "", "b4w_source_size": "128", "b4w_enable_canvas_mipmapping": true, "extension": "REPEAT", "b4w_use_map_parallax": false, "b4w_parallax_scale": 0.02, "b4w_parallax_steps": 5, "b4w_parallax_lod_dist": 5, "b4w_water_foam": false, "b4w_foam_uv_freq": [1, 1], "b4w_foam_uv_magnitude": [1, 1], "b4w_shore_dist_map": false, "b4w_anisotropic_filtering": "DEFAULT", "b4w_shore_boundings": [0, 0, 0, 0], "b4w_max_shore_dist": 100, "b4w_disable_compression": false, "b4w_use_as_skydome": true, "b4w_use_as_environment_lighting": false, "image": {"uuid": "f1e6976b5795d18a8e45fd0e4174724c"}, "frame_duration": 0, "frame_offset": 0, "frame_start": 0, "use_auto_refresh": false, "use_cyclic": false, "movie_length": 0, "b4w_nla_video": false, "noise_intensity": null, "noise_scale": null, "use_color_ramp": false, "color_ramp": null}], "materials": [{"use_orco_tex_coord": false, "name": "old_caucasian_male_detailed", "use_nodes": false, "diffuse_color": [0.8, 0.8, 0.8], "diffuse_shader": "LAMBERT", "roughness": 0.5, "diffuse_fresnel": 0.1, "diffuse_fresnel_factor": 0.5, "darkness": 1, "diffuse_toon_size": 0.5, "diffuse_toon_smooth": 0.1, "diffuse_intensity": 0.8, "alpha": 1, "specular_alpha": 1, "raytrace_mirror": {"reflect_factor": -1, "fresnel": 0, "fresnel_factor": 1.25}, "specular_color": [0.0275, 0.0275, 0.0275], "specular_intensity": 0.5, "specular_shader": "PHONG", "specular_hardness": 128, "specular_ior": 4, "specular_slope": 0.1, "specular_toon_size": 0.5, "specular_toon_smooth": 0.1, "emit": 0, "ambient": 1, "use_vertex_color_paint": false, "b4w_water": false, "b4w_water_shore_smoothing": true, "b4w_water_absorb_factor": 6, "b4w_water_dynamic": false, "b4w_waves_height": 1, "b4w_waves_length": 10, "b4w_generated_mesh": false, "b4w_water_num_cascads": 5, "b4w_water_subdivs": 64, "b4w_water_detailed_dist": 1000, "b4w_water_fog_color": [0.4, 0.6, 0.7], "b4w_water_fog_density": 0.06, "b4w_foam_factor": 0.5, "b4w_shallow_water_col": [0, 0.8, 0.3], "b4w_shore_water_col": [0, 0.9, 0.2], "b4w_shallow_water_col_fac": 1, "b4w_shore_water_col_fac": 0.5, "b4w_water_dst_noise_scale0": 0.05, "b4w_water_dst_noise_scale1": 0.03, "b4w_water_dst_noise_freq0": 1.3, "b4w_water_dst_noise_freq1": 1, "b4w_water_dir_min_shore_fac": 0.4, "b4w_water_dir_freq": 0.5, "b4w_water_dir_noise_scale": 0.05, "b4w_water_dir_noise_freq": 0.07, "b4w_water_dir_min_noise_fac": 0.5, "b4w_water_dst_min_fac": 0.2, "b4w_water_waves_hor_fac": 5, "b4w_water_sss_strength": 1, "b4w_water_sss_width": 0.45, "b4w_water_norm_uv_velocity": 0.05, "b4w_water_enable_caust": false, "b4w_water_caust_scale": 0.25, "b4w_water_caust_brightness": 0.5, "b4w_terrain": false, "b4w_dynamic_grass_size": "", "b4w_dynamic_grass_color": "", "b4w_do_not_render": false, "b4w_lens_flares": false, "b4w_collision": false, "b4w_use_ghost": false, "b4w_collision_id": "", "b4w_collision_margin": 0.03999999910593033, "b4w_collision_group": 128, "b4w_collision_mask": 65407, "b4w_double_sided_lighting": false, "b4w_wettable": false, "b4w_refractive": false, "b4w_refr_bump": 0.0010000000474974513, "b4w_render_above_all": false, "physics": {"friction": 0.5, "elasticity": 0}, "type": "SURFACE", "b4w_halo_sky_stars": false, "b4w_halo_stars_blend_height": 10.0, "b4w_halo_stars_min_height": 0.0, "halo": {"hardness": 128, "size": 0.5, "b4w_halo_rings_color": [1, 1, 1], "b4w_halo_lines_color": [0.0275, 0.0275, 0.0275], "ring_count": 0, "line_count": 0, "star_tip_count": 0}, "use_transparency": false, "use_shadeless": false, "use_tangent_shading": false, "pass_index": 0, "offset_z": 0, "game_settings": {"alpha_blend": "OPAQUE", "use_backface_culling": true}, "uv_vc_key": "man4-base-UV", "node_tree": null, "texture_slots": [{"texture_coords": "UV", "uv_layer": "man4-base-UV", "use_map_color_diffuse": true, "diffuse_color_factor": 1, "use_map_alpha": false, "alpha_factor": 1, "use_map_color_spec": false, "specular_color_factor": 1, "use_map_normal": false, "normal_factor": 1, "use_map_mirror": false, "mirror_factor": 1, "use_rgb_to_intensity": false, "use_stencil": false, "offset": [0, 0, 0], "scale": [1, 1, 1], "blend_type": "MIX", "texture": {"uuid": "25bdad333d00a31d9017c0edfda94cdd"}}], "uuid": "50e348669cfcf6f4460756b587bb4337", "source_uuid": "7939cb5d488277c13659aa74b7982cf2"}, {"use_orco_tex_coord": false, "name": "shoes03", "use_nodes": false, "diffuse_color": [0.8, 0.8, 0.8], "diffuse_shader": "LAMBERT", "roughness": 0.5, "diffuse_fresnel": 0.1, "diffuse_fresnel_factor": 0.5, "darkness": 1, "diffuse_toon_size": 0.5, "diffuse_toon_smooth": 0.1, "diffuse_intensity": 0.8, "alpha": 1, "specular_alpha": 1, "raytrace_mirror": {"reflect_factor": -1, "fresnel": 0, "fresnel_factor": 1.25}, "specular_color": [0.0353, 0.0314, 0.0314], "specular_intensity": 0.5, "specular_shader": "PHONG", "specular_hardness": 204, "specular_ior": 4, "specular_slope": 0.1, "specular_toon_size": 0.5, "specular_toon_smooth": 0.1, "emit": 0, "ambient": 1, "use_vertex_color_paint": false, "b4w_water": false, "b4w_water_shore_smoothing": true, "b4w_water_absorb_factor": 6, "b4w_water_dynamic": false, "b4w_waves_height": 1, "b4w_waves_length": 10, "b4w_generated_mesh": false, "b4w_water_num_cascads": 5, "b4w_water_subdivs": 64, "b4w_water_detailed_dist": 1000, "b4w_water_fog_color": [0.4, 0.6, 0.7], "b4w_water_fog_density": 0.06, "b4w_foam_factor": 0.5, "b4w_shallow_water_col": [0, 0.8, 0.3], "b4w_shore_water_col": [0, 0.9, 0.2], "b4w_shallow_water_col_fac": 1, "b4w_shore_water_col_fac": 0.5, "b4w_water_dst_noise_scale0": 0.05, "b4w_water_dst_noise_scale1": 0.03, "b4w_water_dst_noise_freq0": 1.3, "b4w_water_dst_noise_freq1": 1, "b4w_water_dir_min_shore_fac": 0.4, "b4w_water_dir_freq": 0.5, "b4w_water_dir_noise_scale": 0.05, "b4w_water_dir_noise_freq": 0.07, "b4w_water_dir_min_noise_fac": 0.5, "b4w_water_dst_min_fac": 0.2, "b4w_water_waves_hor_fac": 5, "b4w_water_sss_strength": 1, "b4w_water_sss_width": 0.45, "b4w_water_norm_uv_velocity": 0.05, "b4w_water_enable_caust": false, "b4w_water_caust_scale": 0.25, "b4w_water_caust_brightness": 0.5, "b4w_terrain": false, "b4w_dynamic_grass_size": "", "b4w_dynamic_grass_color": "", "b4w_do_not_render": false, "b4w_lens_flares": false, "b4w_collision": false, "b4w_use_ghost": false, "b4w_collision_id": "", "b4w_collision_margin": 0.03999999910593033, "b4w_collision_group": 128, "b4w_collision_mask": 65407, "b4w_double_sided_lighting": false, "b4w_wettable": false, "b4w_refractive": false, "b4w_refr_bump": 0.0010000000474974513, "b4w_render_above_all": false, "physics": {"friction": 0.5, "elasticity": 0}, "type": "SURFACE", "b4w_halo_sky_stars": false, "b4w_halo_stars_blend_height": 10.0, "b4w_halo_stars_min_height": 0.0, "halo": {"hardness": 204, "size": 0.5, "b4w_halo_rings_color": [1, 1, 1], "b4w_halo_lines_color": [0.0353, 0.0314, 0.0314], "ring_count": 0, "line_count": 0, "star_tip_count": 0}, "use_transparency": false, "use_shadeless": false, "use_tangent_shading": false, "pass_index": 0, "offset_z": 0, "game_settings": {"alpha_blend": "OPAQUE", "use_backface_culling": true}, "uv_vc_key": "man4-shoes03-UV", "node_tree": null, "texture_slots": [{"texture_coords": "UV", "uv_layer": "man4-shoes03-UV", "use_map_color_diffuse": true, "diffuse_color_factor": 1, "use_map_alpha": false, "alpha_factor": 1, "use_map_color_spec": false, "specular_color_factor": 1, "use_map_normal": false, "normal_factor": 1, "use_map_mirror": false, "mirror_factor": 1, "use_rgb_to_intensity": false, "use_stencil": false, "offset": [0, 0, 0], "scale": [1, 1, 1], "blend_type": "MIX", "texture": {"uuid": "84a1fb4484b4e84346afe0cacc9da844"}}], "uuid": "5f78a8d30a6afe57412f47992dc36c00", "source_uuid": "10b9a29028581c917c6f9ba9e1708212"}, {"use_orco_tex_coord": false, "name": "Male_casualsuit01", "use_nodes": false, "diffuse_color": [0.8, 0.8, 0.8], "diffuse_shader": "LAMBERT", "roughness": 0.5, "diffuse_fresnel": 0.1, "diffuse_fresnel_factor": 0.5, "darkness": 1, "diffuse_toon_size": 0.5, "diffuse_toon_smooth": 0.1, "diffuse_intensity": 0.8, "alpha": 1, "specular_alpha": 1, "raytrace_mirror": {"reflect_factor": -1, "fresnel": 0, "fresnel_factor": 1.25}, "specular_color": [1, 1, 1], "specular_intensity": 0, "specular_shader": "PHONG", "specular_hardness": 51, "specular_ior": 4, "specular_slope": 0.1, "specular_toon_size": 0.5, "specular_toon_smooth": 0.1, "emit": 0, "ambient": 1, "use_vertex_color_paint": false, "b4w_water": false, "b4w_water_shore_smoothing": true, "b4w_water_absorb_factor": 6, "b4w_water_dynamic": false, "b4w_waves_height": 1, "b4w_waves_length": 10, "b4w_generated_mesh": false, "b4w_water_num_cascads": 5, "b4w_water_subdivs": 64, "b4w_water_detailed_dist": 1000, "b4w_water_fog_color": [0.4, 0.6, 0.7], "b4w_water_fog_density": 0.06, "b4w_foam_factor": 0.5, "b4w_shallow_water_col": [0, 0.8, 0.3], "b4w_shore_water_col": [0, 0.9, 0.2], "b4w_shallow_water_col_fac": 1, "b4w_shore_water_col_fac": 0.5, "b4w_water_dst_noise_scale0": 0.05, "b4w_water_dst_noise_scale1": 0.03, "b4w_water_dst_noise_freq0": 1.3, "b4w_water_dst_noise_freq1": 1, "b4w_water_dir_min_shore_fac": 0.4, "b4w_water_dir_freq": 0.5, "b4w_water_dir_noise_scale": 0.05, "b4w_water_dir_noise_freq": 0.07, "b4w_water_dir_min_noise_fac": 0.5, "b4w_water_dst_min_fac": 0.2, "b4w_water_waves_hor_fac": 5, "b4w_water_sss_strength": 1, "b4w_water_sss_width": 0.45, "b4w_water_norm_uv_velocity": 0.05, "b4w_water_enable_caust": false, "b4w_water_caust_scale": 0.25, "b4w_water_caust_brightness": 0.5, "b4w_terrain": false, "b4w_dynamic_grass_size": "", "b4w_dynamic_grass_color": "", "b4w_do_not_render": false, "b4w_lens_flares": false, "b4w_collision": false, "b4w_use_ghost": false, "b4w_collision_id": "", "b4w_collision_margin": 0.03999999910593033, "b4w_collision_group": 128, "b4w_collision_mask": 65407, "b4w_double_sided_lighting": false, "b4w_wettable": false, "b4w_refractive": false, "b4w_refr_bump": 0.0010000000474974513, "b4w_render_above_all": false, "physics": {"friction": 0.5, "elasticity": 0}, "type": "SURFACE", "b4w_halo_sky_stars": false, "b4w_halo_stars_blend_height": 10.0, "b4w_halo_stars_min_height": 0.0, "halo": {"hardness": 51, "size": 0.5, "b4w_halo_rings_color": [1, 1, 1], "b4w_halo_lines_color": [1, 1, 1], "ring_count": 0, "line_count": 0, "star_tip_count": 0}, "use_transparency": false, "use_shadeless": false, "use_tangent_shading": false, "pass_index": 0, "offset_z": 0, "game_settings": {"alpha_blend": "OPAQUE", "use_backface_culling": true}, "uv_vc_key": "man4-male_casualsuit01-UV", "node_tree": null, "texture_slots": [{"texture_coords": "UV", "uv_layer": "man4-male_casualsuit01-UV", "use_map_color_diffuse": true, "diffuse_color_factor": 1, "use_map_alpha": false, "alpha_factor": 1, "use_map_color_spec": false, "specular_color_factor": 1, "use_map_normal": false, "normal_factor": 1, "use_map_mirror": false, "mirror_factor": 1, "use_rgb_to_intensity": false, "use_stencil": false, "offset": [0, 0, 0], "scale": [1, 1, 1], "blend_type": "MIX", "texture": {"uuid": "e3ebc15a047d097018b6b418bd9aa10c"}}], "uuid": "2b6dd94f3751024ea128c5da0dc143e8", "source_uuid": "add0e20da06b5fa42ba412b7ccf188a8"}, {"use_orco_tex_coord": false, "name": "teethMaterial", "use_nodes": false, "diffuse_color": [0.8, 0.8, 0.8], "diffuse_shader": "LAMBERT", "roughness": 0.5, "diffuse_fresnel": 0.1, "diffuse_fresnel_factor": 0.5, "darkness": 1, "diffuse_toon_size": 0.5, "diffuse_toon_smooth": 0.1, "diffuse_intensity": 0.8, "alpha": 1, "specular_alpha": 1, "raytrace_mirror": {"reflect_factor": -1, "fresnel": 0, "fresnel_factor": 1.25}, "specular_color": [0.8549, 0.8549, 0.8549], "specular_intensity": 0.5, "specular_shader": "PHONG", "specular_hardness": 204, "specular_ior": 4, "specular_slope": 0.1, "specular_toon_size": 0.5, "specular_toon_smooth": 0.1, "emit": 0, "ambient": 1, "use_vertex_color_paint": false, "b4w_water": false, "b4w_water_shore_smoothing": true, "b4w_water_absorb_factor": 6, "b4w_water_dynamic": false, "b4w_waves_height": 1, "b4w_waves_length": 10, "b4w_generated_mesh": false, "b4w_water_num_cascads": 5, "b4w_water_subdivs": 64, "b4w_water_detailed_dist": 1000, "b4w_water_fog_color": [0.4, 0.6, 0.7], "b4w_water_fog_density": 0.06, "b4w_foam_factor": 0.5, "b4w_shallow_water_col": [0, 0.8, 0.3], "b4w_shore_water_col": [0, 0.9, 0.2], "b4w_shallow_water_col_fac": 1, "b4w_shore_water_col_fac": 0.5, "b4w_water_dst_noise_scale0": 0.05, "b4w_water_dst_noise_scale1": 0.03, "b4w_water_dst_noise_freq0": 1.3, "b4w_water_dst_noise_freq1": 1, "b4w_water_dir_min_shore_fac": 0.4, "b4w_water_dir_freq": 0.5, "b4w_water_dir_noise_scale": 0.05, "b4w_water_dir_noise_freq": 0.07, "b4w_water_dir_min_noise_fac": 0.5, "b4w_water_dst_min_fac": 0.2, "b4w_water_waves_hor_fac": 5, "b4w_water_sss_strength": 1, "b4w_water_sss_width": 0.45, "b4w_water_norm_uv_velocity": 0.05, "b4w_water_enable_caust": false, "b4w_water_caust_scale": 0.25, "b4w_water_caust_brightness": 0.5, "b4w_terrain": false, "b4w_dynamic_grass_size": "", "b4w_dynamic_grass_color": "", "b4w_do_not_render": false, "b4w_lens_flares": false, "b4w_collision": false, "b4w_use_ghost": false, "b4w_collision_id": "", "b4w_collision_margin": 0.03999999910593033, "b4w_collision_group": 128, "b4w_collision_mask": 65407, "b4w_double_sided_lighting": false, "b4w_wettable": false, "b4w_refractive": false, "b4w_refr_bump": 0.0010000000474974513, "b4w_render_above_all": false, "physics": {"friction": 0.5, "elasticity": 0}, "type": "SURFACE", "b4w_halo_sky_stars": false, "b4w_halo_stars_blend_height": 10.0, "b4w_halo_stars_min_height": 0.0, "halo": {"hardness": 204, "size": 0.5, "b4w_halo_rings_color": [1, 1, 1], "b4w_halo_lines_color": [0.8549, 0.8549, 0.8549], "ring_count": 0, "line_count": 0, "star_tip_count": 0}, "use_transparency": false, "use_shadeless": false, "use_tangent_shading": false, "pass_index": 0, "offset_z": 0, "game_settings": {"alpha_blend": "OPAQUE", "use_backface_culling": true}, "uv_vc_key": "man4-teeth_shape02-UV", "node_tree": null, "texture_slots": [{"texture_coords": "UV", "uv_layer": "man4-teeth_shape02-UV", "use_map_color_diffuse": true, "diffuse_color_factor": 1, "use_map_alpha": false, "alpha_factor": 1, "use_map_color_spec": false, "specular_color_factor": 1, "use_map_normal": false, "normal_factor": 1, "use_map_mirror": false, "mirror_factor": 1, "use_rgb_to_intensity": false, "use_stencil": false, "offset": [0, 0, 0], "scale": [1, 1, 1], "blend_type": "MIX", "texture": {"uuid": "b424db2696230583fd8aa11aeb99d506"}}], "uuid": "54290a7fbc752a3c1e62f7896ab87762", "source_uuid": "081282a3559719fbe87a21454fb48fb6"}, {"use_orco_tex_coord": false, "name": "eyebrow012", "use_nodes": false, "diffuse_color": [0.4141, 0.2366, 0.1488], "diffuse_shader": "LAMBERT", "roughness": 0.5, "diffuse_fresnel": 0.1, "diffuse_fresnel_factor": 0.5, "darkness": 1, "diffuse_toon_size": 0.5, "diffuse_toon_smooth": 0.1, "diffuse_intensity": 0.781, "alpha": 0.7585, "specular_alpha": 1, "raytrace_mirror": {"reflect_factor": -1, "fresnel": 0, "fresnel_factor": 1.25}, "specular_color": [0, 0, 0], "specular_intensity": 0.5, "specular_shader": "PHONG", "specular_hardness": 128, "specular_ior": 4, "specular_slope": 0.1, "specular_toon_size": 0.5, "specular_toon_smooth": 0.1, "emit": 0, "ambient": 1, "use_vertex_color_paint": false, "b4w_water": false, "b4w_water_shore_smoothing": true, "b4w_water_absorb_factor": 6, "b4w_water_dynamic": false, "b4w_waves_height": 1, "b4w_waves_length": 10, "b4w_generated_mesh": false, "b4w_water_num_cascads": 5, "b4w_water_subdivs": 64, "b4w_water_detailed_dist": 1000, "b4w_water_fog_color": [0.4, 0.6, 0.7], "b4w_water_fog_density": 0.06, "b4w_foam_factor": 0.5, "b4w_shallow_water_col": [0, 0.8, 0.3], "b4w_shore_water_col": [0, 0.9, 0.2], "b4w_shallow_water_col_fac": 1, "b4w_shore_water_col_fac": 0.5, "b4w_water_dst_noise_scale0": 0.05, "b4w_water_dst_noise_scale1": 0.03, "b4w_water_dst_noise_freq0": 1.3, "b4w_water_dst_noise_freq1": 1, "b4w_water_dir_min_shore_fac": 0.4, "b4w_water_dir_freq": 0.5, "b4w_water_dir_noise_scale": 0.05, "b4w_water_dir_noise_freq": 0.07, "b4w_water_dir_min_noise_fac": 0.5, "b4w_water_dst_min_fac": 0.2, "b4w_water_waves_hor_fac": 5, "b4w_water_sss_strength": 1, "b4w_water_sss_width": 0.45, "b4w_water_norm_uv_velocity": 0.05, "b4w_water_enable_caust": false, "b4w_water_caust_scale": 0.25, "b4w_water_caust_brightness": 0.5, "b4w_terrain": false, "b4w_dynamic_grass_size": "", "b4w_dynamic_grass_color": "", "b4w_do_not_render": false, "b4w_lens_flares": false, "b4w_collision": false, "b4w_use_ghost": false, "b4w_collision_id": "", "b4w_collision_margin": 0.03999999910593033, "b4w_collision_group": 128, "b4w_collision_mask": 65407, "b4w_double_sided_lighting": false, "b4w_wettable": false, "b4w_refractive": false, "b4w_refr_bump": 0.0010000000474974513, "b4w_render_above_all": false, "physics": {"friction": 0.5, "elasticity": 0}, "type": "SURFACE", "b4w_halo_sky_stars": false, "b4w_halo_stars_blend_height": 10.0, "b4w_halo_stars_min_height": 0.0, "halo": {"hardness": 128, "size": 0.5, "b4w_halo_rings_color": [1, 1, 1], "b4w_halo_lines_color": [0, 0, 0], "ring_count": 0, "line_count": 0, "star_tip_count": 0}, "use_transparency": true, "use_shadeless": false, "use_tangent_shading": false, "pass_index": 0, "offset_z": 0, "game_settings": {"alpha_blend": "OPAQUE", "use_backface_culling": true}, "uv_vc_key": "man4-eyebrow012-UV", "node_tree": null, "texture_slots": [{"texture_coords": "UV", "uv_layer": "man4-eyebrow012-UV", "use_map_color_diffuse": true, "diffuse_color_factor": 1, "use_map_alpha": false, "alpha_factor": 1, "use_map_color_spec": false, "specular_color_factor": 1, "use_map_normal": false, "normal_factor": 1, "use_map_mirror": false, "mirror_factor": 1, "use_rgb_to_intensity": false, "use_stencil": false, "offset": [0, 0, 0], "scale": [1, 1, 1], "blend_type": "MIX", "texture": {"uuid": "fbec5bafed75899e5c33c86605973e5d"}}], "uuid": "9f59ac7db23d92a7ab70b30ab294e032", "source_uuid": "ee64f5cdbea0c7ac007a0e203ca8b0f2"}, {"use_orco_tex_coord": false, "name": "Eye_brown", "use_nodes": false, "diffuse_color": [0.8, 0.8, 0.8], "diffuse_shader": "LAMBERT", "roughness": 0.5, "diffuse_fresnel": 0.1, "diffuse_fresnel_factor": 0.5, "darkness": 1, "diffuse_toon_size": 0.5, "diffuse_toon_smooth": 0.1, "diffuse_intensity": 0.8, "alpha": 1, "specular_alpha": 1, "raytrace_mirror": {"reflect_factor": -1, "fresnel": 0, "fresnel_factor": 1.25}, "specular_color": [1, 1, 1], "specular_intensity": 0.5, "specular_shader": "PHONG", "specular_hardness": 256, "specular_ior": 4, "specular_slope": 0.1, "specular_toon_size": 0.5, "specular_toon_smooth": 0.1, "emit": 0, "ambient": 1, "use_vertex_color_paint": false, "b4w_water": false, "b4w_water_shore_smoothing": true, "b4w_water_absorb_factor": 6, "b4w_water_dynamic": false, "b4w_waves_height": 1, "b4w_waves_length": 10, "b4w_generated_mesh": false, "b4w_water_num_cascads": 5, "b4w_water_subdivs": 64, "b4w_water_detailed_dist": 1000, "b4w_water_fog_color": [0.4, 0.6, 0.7], "b4w_water_fog_density": 0.06, "b4w_foam_factor": 0.5, "b4w_shallow_water_col": [0, 0.8, 0.3], "b4w_shore_water_col": [0, 0.9, 0.2], "b4w_shallow_water_col_fac": 1, "b4w_shore_water_col_fac": 0.5, "b4w_water_dst_noise_scale0": 0.05, "b4w_water_dst_noise_scale1": 0.03, "b4w_water_dst_noise_freq0": 1.3, "b4w_water_dst_noise_freq1": 1, "b4w_water_dir_min_shore_fac": 0.4, "b4w_water_dir_freq": 0.5, "b4w_water_dir_noise_scale": 0.05, "b4w_water_dir_noise_freq": 0.07, "b4w_water_dir_min_noise_fac": 0.5, "b4w_water_dst_min_fac": 0.2, "b4w_water_waves_hor_fac": 5, "b4w_water_sss_strength": 1, "b4w_water_sss_width": 0.45, "b4w_water_norm_uv_velocity": 0.05, "b4w_water_enable_caust": false, "b4w_water_caust_scale": 0.25, "b4w_water_caust_brightness": 0.5, "b4w_terrain": false, "b4w_dynamic_grass_size": "", "b4w_dynamic_grass_color": "", "b4w_do_not_render": false, "b4w_lens_flares": false, "b4w_collision": false, "b4w_use_ghost": false, "b4w_collision_id": "", "b4w_collision_margin": 0.03999999910593033, "b4w_collision_group": 128, "b4w_collision_mask": 65407, "b4w_double_sided_lighting": false, "b4w_wettable": false, "b4w_refractive": false, "b4w_refr_bump": 0.0010000000474974513, "b4w_render_above_all": false, "physics": {"friction": 0.5, "elasticity": 0}, "type": "SURFACE", "b4w_halo_sky_stars": false, "b4w_halo_stars_blend_height": 10.0, "b4w_halo_stars_min_height": 0.0, "halo": {"hardness": 256, "size": 0.5, "b4w_halo_rings_color": [1, 1, 1], "b4w_halo_lines_color": [1, 1, 1], "ring_count": 0, "line_count": 0, "star_tip_count": 0}, "use_transparency": false, "use_shadeless": false, "use_tangent_shading": false, "pass_index": 0, "offset_z": 0, "game_settings": {"alpha_blend": "OPAQUE", "use_backface_culling": true}, "uv_vc_key": "man4-low_poly-UV", "node_tree": null, "texture_slots": [{"texture_coords": "UV", "uv_layer": "man4-low_poly-UV", "use_map_color_diffuse": true, "diffuse_color_factor": 1, "use_map_alpha": false, "alpha_factor": 1, "use_map_color_spec": false, "specular_color_factor": 1, "use_map_normal": false, "normal_factor": 1, "use_map_mirror": false, "mirror_factor": 1, "use_rgb_to_intensity": false, "use_stencil": false, "offset": [0, 0, 0], "scale": [1, 1, 1], "blend_type": "MIX", "texture": {"uuid": "f0e6aba741649c10490fcd160043fd86"}}], "uuid": "9d5af7c2afc2791b8b64265ae826bcf9", "source_uuid": "e4a52b1806ad8c34423aa218e87429fd"}, {"use_orco_tex_coord": false, "name": "short02", "use_nodes": false, "diffuse_color": [0.3625, 0.2151, 0.1436], "diffuse_shader": "LAMBERT", "roughness": 0.5, "diffuse_fresnel": 0.1, "diffuse_fresnel_factor": 0.5, "darkness": 1, "diffuse_toon_size": 0.5, "diffuse_toon_smooth": 0.1, "diffuse_intensity": 0.8, "alpha": 1, "specular_alpha": 1, "raytrace_mirror": {"reflect_factor": -1, "fresnel": 0, "fresnel_factor": 1.25}, "specular_color": [0.0911, 0.0911, 0.0911], "specular_intensity": 0.4179, "specular_shader": "PHONG", "specular_hardness": 245, "specular_ior": 4, "specular_slope": 0.1, "specular_toon_size": 0.5, "specular_toon_smooth": 0.1, "emit": 0, "ambient": 1, "use_vertex_color_paint": false, "b4w_water": false, "b4w_water_shore_smoothing": true, "b4w_water_absorb_factor": 6, "b4w_water_dynamic": false, "b4w_waves_height": 1, "b4w_waves_length": 10, "b4w_generated_mesh": false, "b4w_water_num_cascads": 5, "b4w_water_subdivs": 64, "b4w_water_detailed_dist": 1000, "b4w_water_fog_color": [0.4, 0.6, 0.7], "b4w_water_fog_density": 0.06, "b4w_foam_factor": 0.5, "b4w_shallow_water_col": [0, 0.8, 0.3], "b4w_shore_water_col": [0, 0.9, 0.2], "b4w_shallow_water_col_fac": 1, "b4w_shore_water_col_fac": 0.5, "b4w_water_dst_noise_scale0": 0.05, "b4w_water_dst_noise_scale1": 0.03, "b4w_water_dst_noise_freq0": 1.3, "b4w_water_dst_noise_freq1": 1, "b4w_water_dir_min_shore_fac": 0.4, "b4w_water_dir_freq": 0.5, "b4w_water_dir_noise_scale": 0.05, "b4w_water_dir_noise_freq": 0.07, "b4w_water_dir_min_noise_fac": 0.5, "b4w_water_dst_min_fac": 0.2, "b4w_water_waves_hor_fac": 5, "b4w_water_sss_strength": 1, "b4w_water_sss_width": 0.45, "b4w_water_norm_uv_velocity": 0.05, "b4w_water_enable_caust": false, "b4w_water_caust_scale": 0.25, "b4w_water_caust_brightness": 0.5, "b4w_terrain": false, "b4w_dynamic_grass_size": "", "b4w_dynamic_grass_color": "", "b4w_do_not_render": false, "b4w_lens_flares": false, "b4w_collision": false, "b4w_use_ghost": false, "b4w_collision_id": "", "b4w_collision_margin": 0.03999999910593033, "b4w_collision_group": 128, "b4w_collision_mask": 65407, "b4w_double_sided_lighting": false, "b4w_wettable": false, "b4w_refractive": false, "b4w_refr_bump": 0.0010000000474974513, "b4w_render_above_all": false, "physics": {"friction": 0.5, "elasticity": 0}, "type": "SURFACE", "b4w_halo_sky_stars": false, "b4w_halo_stars_blend_height": 10.0, "b4w_halo_stars_min_height": 0.0, "halo": {"hardness": 245, "size": 0.5, "b4w_halo_rings_color": [1, 1, 1], "b4w_halo_lines_color": [0.0911, 0.0911, 0.0911], "ring_count": 0, "line_count": 0, "star_tip_count": 0}, "use_transparency": false, "use_shadeless": false, "use_tangent_shading": false, "pass_index": 0, "offset_z": 0, "game_settings": {"alpha_blend": "OPAQUE", "use_backface_culling": true}, "uv_vc_key": "man4-short02-UV", "node_tree": null, "texture_slots": [{"texture_coords": "UV", "uv_layer": "man4-short02-UV", "use_map_color_diffuse": true, "diffuse_color_factor": 1, "use_map_alpha": false, "alpha_factor": 1, "use_map_color_spec": false, "specular_color_factor": 1, "use_map_normal": false, "normal_factor": 1, "use_map_mirror": false, "mirror_factor": 1, "use_rgb_to_intensity": false, "use_stencil": false, "offset": [0, 0, 0], "scale": [1, 1, 1], "blend_type": "MIX", "texture": {"uuid": "f9674c99eadbb1d85be80cee8ab7ea04"}}], "uuid": "ae54a45e2076217c4d1e1cfa4bb78fb0", "source_uuid": "15e143388fa4ffebb42cff0914626c39"}], "meshes": [{"name": "Sax_Player", "uuid": "dd4f57b719ce37098501f2ef751dd5dd", "materials": [{"uuid": "50e348669cfcf6f4460756b587bb4337"}, {"uuid": "5f78a8d30a6afe57412f47992dc36c00"}, {"uuid": "2b6dd94f3751024ea128c5da0dc143e8"}, {"uuid": "54290a7fbc752a3c1e62f7896ab87762"}, {"uuid": "9f59ac7db23d92a7ab70b30ab294e032"}, {"uuid": "9d5af7c2afc2791b8b64265ae826bcf9"}, {"uuid": "ae54a45e2076217c4d1e1cfa4bb78fb0"}], "b4w_vertex_anim": [], "vertex_groups": [], "uv_textures": ["man4-base-UV", "man4-shoes03-UV", "man4-male_casualsuit01-UV", "man4-teeth_shape02-UV", "man4-eyebrow012-UV", "man4-low_poly-UV", "man4-short02-UV"], "active_vcol_name": "", "active_uv_name": "man4-base-UV", "submeshes": [{"boundings": {"bb": {"max_x": 0.36294, "max_y": 0.17209, "max_z": 1.7589, "min_x": -0.1402, "min_y": -0.15831, "min_z": 1.1174}, "be_ax": [0.36489, 0.28698, 0.63115], "be_cen": [0.10829, 0.00824, 1.45395], "rbb": {"rbb_c": [0.12143927812576294, 0.010069392621517181, 1.428450107574463], "rbb_s": [0.21036630868911743, 0.16545319557189941, 0.36387503147125244]}, "caxis_x": [0.8300970792770386, 0.0, 0.5576188564300537], "caxis_y": [-0.013881380669772625, 0.9996901154518127, 0.020664462819695473], "caxis_z": [-0.5574460625648499, -0.024894030764698982, 0.829839825630188]}, "base_length": 8119, "indices": [0, 40938], "position": [0, 24357], "texcoord": [24357, 16238], "shade_tangs": [0, 0], "normal": [0, 24357], "tangent": [24357, 32476], "group": [0, 0], "color": [0, 0], "vertex_colors": [], "uv_layers": ["man4-base-UV"]}, {"boundings": {"bb": {"max_x": 0.2107, "max_y": 0.1375, "max_z": 0.1576, "min_x": -0.167, "min_y": -0.3731, "min_z": -0.0272}, "be_ax": [0.24911, 0.49494, 0.14584], "be_cen": [0.00487, -0.10657, 0.06437], "rbb": {"rbb_c": [0.04667392000555992, -0.13165515661239624, 0.0455191396176815], "rbb_s": [0.1372656226158142, 0.27272823452949524, 0.08036525547504425]}, "caxis_x": [0.9085574150085449, 0.32267922163009644, -0.2653329074382782], "caxis_y": [-0.33467501401901245, 0.9423335790634155, 0.0], "caxis_z": [0.25003209710121155, 0.08880029618740082, 0.9641568660736084]}, "base_length": 1921, "indices": [40938, 8460], "position": [40595, 5763], "texcoord": [46358, 3842], "shade_tangs": [0, 0], "normal": [56833, 5763], "tangent": [62596, 7684], "group": [0, 0], "color": [0, 0], "vertex_colors": [], "uv_layers": ["man4-shoes03-UV"]}, {"boundings": {"bb": {"max_x": 0.28864, "max_y": 0.33337, "max_z": 1.5634, "min_x": -0.19282, "min_y": -0.3245, "min_z": 0.0831}, "be_ax": [0.42046, 0.51165, 1.34035], "be_cen": [0.03505, -0.00097, 0.8215], "rbb": {"rbb_c": [0.028214143589138985, -0.02864215523004532, 0.8058153986930847], "rbb_s": [0.23677340149879456, 0.2881236672401428, 0.7547911405563354]}, "caxis_x": [0.9850507974624634, 0.16004034876823425, -0.06373435258865356], "caxis_y": [-0.16765184700489044, 0.9756898283958435, -0.14114604890346527], "caxis_z": [0.039595894515514374, 0.1497212052345276, 0.9879351258277893]}, "base_length": 8451, "indices": [49398, 42879], "position": [50200, 25353], "texcoord": [75553, 16902], "shade_tangs": [0, 0], "normal": [70280, 25353], "tangent": [95633, 33804], "group": [0, 0], "color": [0, 0], "vertex_colors": [], "uv_layers": ["man4-male_casualsuit01-UV"]}, {"boundings": {"bb": {"max_x": 0.1035, "max_y": 0.069, "max_z": 1.6099, "min_x": 0.0274, "min_y": -0.0021, "min_z": 1.5492}, "be_ax": [0.0659, 0.06157, 0.05257], "be_cen": [0.06545, 0.03345, 1.57955], "rbb": {"rbb_c": [0.06544996052980423, 0.03344999998807907, 1.57955002784729], "rbb_s": [0.038050033152103424, 0.03554999828338623, 0.030349910259246826]}, "caxis_x": [1.0, 0.0, 0.0], "caxis_y": [0.0, 1.0, 0.0], "caxis_z": [0.0, 0.0, 1.0]}, "base_length": 4497, "indices": [92277, 20076], "position": [92455, 13491], "texcoord": [105946, 8994], "shade_tangs": [0, 0], "normal": [129437, 13491], "tangent": [142928, 17988], "group": [0, 0], "color": [0, 0], "vertex_colors": [], "uv_layers": ["man4-teeth_shape02-UV"]}, {"boundings": {"bb": {"max_x": 0.1073, "max_y": 0.095, "max_z": 1.6788, "min_x": 0.0683, "min_y": -0.0258, "min_z": 1.6523}, "be_ax": [0.03378, 0.10462, 0.02295], "be_cen": [0.0878, 0.0346, 1.66555], "rbb": {"rbb_c": [0.08780000358819962, 0.034599997103214264, 1.6655499935150146], "rbb_s": [0.0195000097155571, 0.06040000170469284, 0.01325005292892456]}, "caxis_x": [1.0, 0.0, 0.0], "caxis_y": [0.0, 1.0, 0.0], "caxis_z": [0.0, 0.0, 1.0]}, "base_length": 123, "indices": [112353, 570], "position": [114940, 369], "texcoord": [115309, 246], "shade_tangs": [0, 0], "normal": [160916, 369], "tangent": [161285, 492], "group": [0, 0], "color": [0, 0], "vertex_colors": [], "uv_layers": ["man4-eyebrow012-UV"]}, {"boundings": {"bb": {"max_x": 0.0962, "max_y": 0.0791, "max_z": 1.6719, "min_x": 0.0655, "min_y": -0.0096, "min_z": 1.6423}, "be_ax": [0.02659, 0.07682, 0.02563], "be_cen": [0.08085, 0.03475, 1.6571], "rbb": {"rbb_c": [0.08084999024868011, 0.03474999964237213, 1.657099962234497], "rbb_s": [0.015349987894296646, 0.044349998235702515, 0.014799952507019043]}, "caxis_x": [1.0, 0.0, 0.0], "caxis_y": [0.0, 1.0, 0.0], "caxis_z": [0.0, 0.0, 1.0]}, "base_length": 96, "indices": [112923, 516], "position": [115555, 288], "texcoord": [115843, 192], "shade_tangs": [0, 0], "normal": [161777, 288], "tangent": [162065, 384], "group": [0, 0], "color": [0, 0], "vertex_colors": [], "uv_layers": ["man4-low_poly-UV"]}, {"boundings": {"bb": {"max_x": 0.10792, "max_y": 0.1261, "max_z": 1.7764, "min_x": -0.09652, "min_y": -0.0724, "min_z": 1.5754}, "be_ax": [0.19881, 0.17246, 0.14732], "be_cen": [0.00253, 0.02685, 1.68074], "rbb": {"rbb_c": [-0.010621488094329834, 0.026850000023841858, 1.689267635345459], "rbb_s": [0.11441388726234436, 0.09925000369548798, 0.08478289842605591]}, "caxis_x": [0.7829077839851379, 0.0, 0.6221377849578857], "caxis_y": [0.0, 1.0, 0.0], "caxis_z": [-0.6221377849578857, 0.0, 0.7829077839851379]}, "base_length": 1725, "indices": [113439, 8694], "position": [116035, 5175], "texcoord": [121210, 3450], "shade_tangs": [0, 0], "normal": [162449, 5175], "tangent": [167624, 6900], "group": [0, 0], "color": [0, 0], "vertex_colors": [], "uv_layers": ["man4-short02-UV"]}], "b4w_shape_keys": [], "b4w_boundings": {"bb": {"max_x": 0.36294, "max_y": 0.33337, "max_z": 1.7764, "min_x": -0.19282, "min_y": -0.3731, "min_z": -0.0272}, "be_ax": [0.48915, 0.52456, 1.61623], "be_cen": [0.06891, -0.00182, 0.86443], "bs_rad": 0.93222, "bc_rad": 0.35981, "bs_cen": [0.08628, -0.02997, 0.84831], "bc_cen": [0.08679, -0.02565, 0.8746], "bb_src": {"max_x": 0.36294, "max_y": 0.33337, "max_z": 1.7764, "min_x": -0.19282, "min_y": -0.3731, "min_z": -0.0272}, "rbb": {"rbb_c": [0.06166473776102066, -0.003871925175189972, 0.8593770861625671], "rbb_s": [0.27576833963394165, 0.2957267165184021, 0.9111752510070801]}, "caxis_x": [0.9990665316581726, -0.004672263748943806, -0.04294445365667343], "caxis_y": [0.0, 0.9941335320472717, -0.10815957188606262], "caxis_z": [0.0431978739798069, 0.10805860906839371, 0.9932055473327637]}, "is_boundings_overridden": false}], "armatures": [], "cameras": [{"name": "Camera.001", "uuid": "31f3bd77848b27cd877bf7b4868d4276", "type": "PERSP", "angle": 0.857556, "angle_y": 0.50338, "sensor_fit": "AUTO", "ortho_scale": 6, "clip_start": 0.1, "clip_end": 100, "dof_distance": 0, "b4w_dof_front_start": 1, "b4w_dof_front_end": 5, "b4w_dof_rear_start": 1, "b4w_dof_rear_end": 5, "b4w_dof_power": 2, "b4w_dof_bokeh": false, "b4w_dof_bokeh_intensity": 0.3, "b4w_dof_foreground_blur": false, "b4w_move_style": "TARGET", "b4w_hover_zero_level": 0.0, "b4w_trans_velocity": 1, "b4w_rot_velocity": 1, "b4w_zoom_velocity": 0.1, "b4w_use_target_distance_limits": false, "b4w_distance_min": 1, "b4w_distance_max": 10, "b4w_use_horizontal_clamping": false, "b4w_rotation_left_limit": -0.7853981852531433, "b4w_rotation_right_limit": 0.7853981852531433, "b4w_horizontal_clamping_type": "LOCAL", "b4w_use_vertical_clamping": false, "b4w_rotation_down_limit": -0.7853981852531433, "b4w_rotation_up_limit": 0.7853981852531433, "b4w_vertical_clamping_type": "LOCAL", "b4w_horizontal_translation_min": -10, "b4w_horizontal_translation_max": 10, "b4w_vertical_translation_min": -10, "b4w_vertical_translation_max": 10, "b4w_use_zooming": false, "b4w_hover_angle_min": 0.0, "b4w_hover_angle_max": 1.5707963705062866, "b4w_enable_hover_hor_rotation": true, "b4w_use_panning": true, "b4w_use_pivot_limits": false, "b4w_pivot_z_min": 0.0, "b4w_pivot_z_max": 10.0, "b4w_target": [0, 0, 0], "dof_object": null}], "curves": [], "lamps": [{"animation_data": null, "name": "Point", "uuid": "bc2f7b8fe4b95041c3d5d12d914ef2b4", "type": "POINT", "energy": 1, "distance": 25, "use_diffuse": true, "use_specular": true, "falloff_type": "INVERSE_SQUARE", "clip_start": 0.5, "clip_end": 40.0, "use_sphere": false, "spot_size": null, "spot_blend": null, "b4w_generate_shadows": false, "b4w_dynamic_intensity": false, "color": [1, 1, 1]}], "sounds": [], "speakers": [], "particles": [], "objects": [{"name": "Sax_player", "uuid": "e455ad39c07645e294567be7b9142713", "type": "MESH", "body_text": null, "data": {"uuid": "dd4f57b719ce37098501f2ef751dd5dd"}, "proxy": null, "dupli_group": null, "parent": null, "b4w_viewport_alignment": null, "pinverse_tsr": null, "parent_type": "OBJECT", "parent_bone": "", "b4w_cluster_data": {"cluster_id": -1, "cluster_center": null, "cluster_radius": 0}, "modifiers": [], "constraints": [], "particle_systems": [], "animation_data": null, "b4w_do_not_batch": true, "b4w_dynamic_geometry": false, "b4w_do_not_cull": false, "b4w_disable_fogging": false, "b4w_do_not_render": false, "b4w_hidden_on_load": false, "b4w_hide_chldr_on_load": false, "b4w_shadow_cast": false, "b4w_shadow_receive": false, "b4w_reflexible": false, "b4w_reflexible_only": false, "b4w_reflective": false, "b4w_reflection_type": "PLANE", "b4w_caustics": false, "b4w_wind_bending": false, "b4w_wind_bending_angle": 10, "b4w_wind_bending_freq": 0.25, "b4w_detail_bending_amp": 0.1, "b4w_detail_bending_freq": 1, "b4w_branch_bending_amp": 0.3, "b4w_main_bend_stiffness_col": "", "b4w_detail_bend_colors": {"leaves_stiffness_col": "", "leaves_phase_col": "", "overall_stiffness_col": ""}, "lod_levels": [], "b4w_proxy_inherit_anim": true, "b4w_selectable": true, "b4w_outlining": true, "b4w_billboard": false, "b4w_pres_glob_orientation": false, "b4w_billboard_geometry": "SPHERICAL", "b4w_outline_settings": {"outline_duration": 1, "outline_period": 1, "outline_relapses": 0}, "b4w_outline_on_select": false, "b4w_use_default_animation": false, "b4w_anim_behavior": "CYCLIC", "b4w_animation_mixing": false, "b4w_shadow_cast_only": false, "b4w_collision": true, "b4w_collision_id": "MUSICOBJ", "b4w_vehicle": false, "b4w_vehicle_settings": null, "b4w_character": false, "b4w_character_settings": null, "b4w_floating": false, "b4w_floating_settings": null, "pose": null, "field": null, "b4w_correct_bounding_offset": "AUTO", "game": {"physics_type": "STATIC", "use_ghost": true, "use_sleep": false, "mass": 1, "velocity_min": 0, "velocity_max": 0, "damping": 0.04, "rotation_damping": 0.1, "lock_location_x": false, "lock_location_y": false, "lock_location_z": false, "lock_rotation_x": false, "lock_rotation_y": false, "lock_rotation_z": false, "collision_margin": 0.03999999910593033, "collision_group": 1, "collision_mask": 65535, "use_collision_bounds": true, "collision_bounds_type": "BOX", "use_collision_compound": false}, "pass_index": 0, "location": [0, 0, 0], "rotation_quaternion": [1, 0, 0, 0], "scale": [1, 1, 1], "b4w_object_tags": null, "b4w_custom_prop": null, "b4w_anchor": null}, {"name": "Empty", "uuid": "6dfabcd6a7670d5be14bd0ebd97c3274", "type": "EMPTY", "body_text": null, "data": "", "proxy": null, "dupli_group": null, "parent": {"uuid": "e455ad39c07645e294567be7b9142713"}, "b4w_viewport_alignment": null, "parent_type": "OBJECT", "parent_bone": "", "b4w_cluster_data": {"cluster_id": -1, "cluster_center": null, "cluster_radius": 0}, "modifiers": [], "constraints": [], "particle_systems": [], "animation_data": null, "b4w_do_not_batch": false, "b4w_dynamic_geometry": false, "b4w_do_not_cull": false, "b4w_disable_fogging": false, "b4w_do_not_render": false, "b4w_hidden_on_load": false, "b4w_hide_chldr_on_load": false, "b4w_shadow_cast": false, "b4w_shadow_receive": false, "b4w_reflexible": false, "b4w_reflexible_only": false, "b4w_reflective": false, "b4w_reflection_type": "PLANE", "b4w_caustics": false, "b4w_wind_bending": false, "b4w_wind_bending_angle": 10, "b4w_wind_bending_freq": 0.25, "b4w_detail_bending_amp": 0.1, "b4w_detail_bending_freq": 1, "b4w_branch_bending_amp": 0.3, "b4w_main_bend_stiffness_col": "", "b4w_detail_bend_colors": {"leaves_stiffness_col": "", "leaves_phase_col": "", "overall_stiffness_col": ""}, "lod_levels": [], "b4w_proxy_inherit_anim": true, "b4w_selectable": false, "b4w_outlining": false, "b4w_billboard": false, "b4w_pres_glob_orientation": false, "b4w_billboard_geometry": "SPHERICAL", "b4w_outline_settings": {"outline_duration": 1, "outline_period": 1, "outline_relapses": 0}, "b4w_outline_on_select": false, "b4w_use_default_animation": false, "b4w_anim_behavior": "CYCLIC", "b4w_animation_mixing": false, "b4w_shadow_cast_only": false, "b4w_collision": false, "b4w_collision_id": "", "b4w_vehicle": false, "b4w_vehicle_settings": null, "b4w_character": false, "b4w_character_settings": null, "b4w_floating": false, "b4w_floating_settings": null, "pose": null, "field": null, "b4w_correct_bounding_offset": "AUTO", "game": {"physics_type": "NO_COLLISION", "use_ghost": false, "use_sleep": false, "mass": 1, "velocity_min": 0, "velocity_max": 0, "damping": 0.04, "rotation_damping": 0.1, "lock_location_x": false, "lock_location_y": false, "lock_location_z": false, "lock_rotation_x": false, "lock_rotation_y": false, "lock_rotation_z": false, "collision_margin": 0.03999999910593033, "collision_group": 1, "collision_mask": 65535, "use_collision_bounds": false, "collision_bounds_type": "BOX", "use_collision_compound": false}, "pass_index": 0, "pinverse_tsr": [0, 0, 0, 1, 0, 0, 0, 1], "location": [0.06525, 0.14216, 1.42671], "rotation_quaternion": [1, 0, 0, 0], "scale": [1, 1, 1], "b4w_object_tags": null, "b4w_custom_prop": null, "b4w_anchor": {"type": "GENERIC", "detect_visibility": false, "element_id": "", "max_width": 250}}, {"name": "Camera", "uuid": "6cf302fed78f9a25c039398e9a8123b9", "type": "CAMERA", "body_text": null, "data": {"uuid": "31f3bd77848b27cd877bf7b4868d4276"}, "proxy": null, "dupli_group": null, "parent": null, "b4w_viewport_alignment": null, "pinverse_tsr": null, "parent_type": "OBJECT", "parent_bone": "", "b4w_cluster_data": {"cluster_id": -1, "cluster_center": null, "cluster_radius": 0}, "modifiers": [], "constraints": [], "particle_systems": [], "animation_data": null, "b4w_do_not_batch": false, "b4w_dynamic_geometry": false, "b4w_do_not_cull": false, "b4w_disable_fogging": false, "b4w_do_not_render": false, "b4w_hidden_on_load": false, "b4w_hide_chldr_on_load": false, "b4w_shadow_cast": false, "b4w_shadow_receive": false, "b4w_reflexible": false, "b4w_reflexible_only": false, "b4w_reflective": false, "b4w_reflection_type": "PLANE", "b4w_caustics": false, "b4w_wind_bending": false, "b4w_wind_bending_angle": 10, "b4w_wind_bending_freq": 0.25, "b4w_detail_bending_amp": 0.1, "b4w_detail_bending_freq": 1, "b4w_branch_bending_amp": 0.3, "b4w_main_bend_stiffness_col": "", "b4w_detail_bend_colors": {"leaves_stiffness_col": "", "leaves_phase_col": "", "overall_stiffness_col": ""}, "lod_levels": [], "b4w_proxy_inherit_anim": true, "b4w_selectable": false, "b4w_outlining": false, "b4w_billboard": false, "b4w_pres_glob_orientation": false, "b4w_billboard_geometry": "SPHERICAL", "b4w_outline_settings": {"outline_duration": 1, "outline_period": 1, "outline_relapses": 0}, "b4w_outline_on_select": false, "b4w_use_default_animation": false, "b4w_anim_behavior": "CYCLIC", "b4w_animation_mixing": false, "b4w_shadow_cast_only": false, "b4w_collision": false, "b4w_collision_id": "", "b4w_vehicle": false, "b4w_vehicle_settings": null, "b4w_character": false, "b4w_character_settings": null, "b4w_floating": false, "b4w_floating_settings": null, "pose": null, "field": null, "b4w_correct_bounding_offset": "AUTO", "game": {"physics_type": "NO_COLLISION", "use_ghost": false, "use_sleep": false, "mass": 1, "velocity_min": 0, "velocity_max": 0, "damping": 0.04, "rotation_damping": 0.1, "lock_location_x": false, "lock_location_y": false, "lock_location_z": false, "lock_rotation_x": false, "lock_rotation_y": false, "lock_rotation_z": false, "collision_margin": 0.03999999910593033, "collision_group": 1, "collision_mask": 65535, "use_collision_bounds": false, "collision_bounds_type": "BOX", "use_collision_compound": false}, "pass_index": 0, "location": [3.72819, -2.39711, 3.06614], "rotation_quaternion": [0.73786, 0.48934, 0.23957, 0.39839], "scale": [1, 1, 1], "b4w_object_tags": null, "b4w_custom_prop": null, "b4w_anchor": null}, {"name": "Point", "uuid": "92b182865f96cec9fce3b77ac1ca4aa2", "type": "LAMP", "body_text": null, "data": {"uuid": "bc2f7b8fe4b95041c3d5d12d914ef2b4"}, "proxy": null, "dupli_group": null, "parent": null, "b4w_viewport_alignment": null, "pinverse_tsr": null, "parent_type": "OBJECT", "parent_bone": "", "b4w_cluster_data": {"cluster_id": -1, "cluster_center": null, "cluster_radius": 0}, "modifiers": [], "constraints": [], "particle_systems": [], "animation_data": null, "b4w_do_not_batch": false, "b4w_dynamic_geometry": false, "b4w_do_not_cull": false, "b4w_disable_fogging": false, "b4w_do_not_render": false, "b4w_hidden_on_load": false, "b4w_hide_chldr_on_load": false, "b4w_shadow_cast": false, "b4w_shadow_receive": false, "b4w_reflexible": false, "b4w_reflexible_only": false, "b4w_reflective": false, "b4w_reflection_type": "PLANE", "b4w_caustics": false, "b4w_wind_bending": false, "b4w_wind_bending_angle": 10, "b4w_wind_bending_freq": 0.25, "b4w_detail_bending_amp": 0.1, "b4w_detail_bending_freq": 1, "b4w_branch_bending_amp": 0.3, "b4w_main_bend_stiffness_col": "", "b4w_detail_bend_colors": {"leaves_stiffness_col": "", "leaves_phase_col": "", "overall_stiffness_col": ""}, "lod_levels": [], "b4w_proxy_inherit_anim": true, "b4w_selectable": false, "b4w_outlining": false, "b4w_billboard": false, "b4w_pres_glob_orientation": false, "b4w_billboard_geometry": "SPHERICAL", "b4w_outline_settings": {"outline_duration": 1, "outline_period": 1, "outline_relapses": 0}, "b4w_outline_on_select": false, "b4w_use_default_animation": false, "b4w_anim_behavior": "CYCLIC", "b4w_animation_mixing": false, "b4w_shadow_cast_only": false, "b4w_collision": false, "b4w_collision_id": "", "b4w_vehicle": false, "b4w_vehicle_settings": null, "b4w_character": false, "b4w_character_settings": null, "b4w_floating": false, "b4w_floating_settings": null, "pose": null, "field": null, "b4w_correct_bounding_offset": "AUTO", "game": {"physics_type": "NO_COLLISION", "use_ghost": false, "use_sleep": false, "mass": 1, "velocity_min": 0, "velocity_max": 0, "damping": 0.04, "rotation_damping": 0.1, "lock_location_x": false, "lock_location_y": false, "lock_location_z": false, "lock_rotation_x": false, "lock_rotation_y": false, "lock_rotation_z": false, "collision_margin": 0.03999999910593033, "collision_group": 1, "collision_mask": 65535, "use_collision_bounds": false, "collision_bounds_type": "BOX", "use_collision_compound": false}, "pass_index": 0, "location": [0.97636, -1.54012, 2.34484], "rotation_quaternion": [1, 0, 0, 0], "scale": [1, 1, 1], "b4w_object_tags": null, "b4w_custom_prop": null, "b4w_anchor": null}], "groups": [], "scenes": [{"name": "Scene", "uuid": "e06c38b34ede5a92f78975f1b4820742", "b4w_use_nla": false, "b4w_nla_cyclic": false, "b4w_logic_nodes": [], "b4w_use_logic_editor": false, "b4w_enable_dynamic_compressor": false, "b4w_dynamic_compressor_settings": {"threshold": -24, "knee": 30, "ratio": 12, "attack": 0.003, "release": 0.25}, "b4w_shadow_settings": {"csm_resolution": 2048, "blur_samples": "16x", "soft_shadows": true, "self_shadow_polygon_offset": 1, "self_shadow_normal_offset": 0.01, "b4w_enable_csm": false, "csm_num": 1, "csm_first_cascade_border": 10, "first_cascade_blur_radius": 3, "csm_last_cascade_border": 100, "last_cascade_blur_radius": 1.5, "fade_last_cascade": true, "blend_between_cascades": true}, "b4w_god_rays_settings": {"intensity": 0.7, "max_ray_length": 1, "steps_per_pass": 10}, "b4w_ssao_settings": {"radius_increase": 3, "hemisphere": false, "blur_depth": false, "blur_discard_value": 1, "influence": 0.7, "dist_factor": 0, "samples": 16}, "b4w_color_correction_settings": {"brightness": 0, "contrast": 0, "exposure": 1, "saturation": 1}, "b4w_bloom_settings": {"key": 1, "blur": 4, "edge_lum": 1, "adaptive": true, "average_luminance": 0.5}, "b4w_motion_blur_settings": {"motion_blur_factor": 0.01, "motion_blur_decay_threshold": 0.01}, "b4w_glow_settings": {"render_glow_over_blend": false, "small_glow_mask_coeff": 2, "large_glow_mask_coeff": 2, "small_glow_mask_width": 2, "large_glow_mask_width": 6}, "b4w_outline_color": [1, 1, 1], "b4w_outline_factor": 1, "b4w_enable_physics": "AUTO", "b4w_render_shadows": "AUTO", "b4w_render_reflections": "ON", "b4w_reflection_quality": "MEDIUM", "b4w_render_refractions": "AUTO", "b4w_render_dynamic_grass": "AUTO", "b4w_enable_god_rays": false, "b4w_enable_glow_materials": "AUTO", "b4w_enable_ssao": false, "b4w_batch_grid_size": 0, "b4w_anisotropic_filtering": "OFF", "b4w_enable_bloom": false, "b4w_enable_motion_blur": false, "b4w_enable_color_correction": false, "b4w_antialiasing_quality": "MEDIUM", "b4w_enable_object_selection": "AUTO", "b4w_enable_outlining": "AUTO", "b4w_enable_anchors_visibility": "AUTO", "b4w_lod_smooth_type": "NON-OPAQUE", "b4w_lod_hyst_interval": 4.0, "b4w_tags": null, "b4w_custom_prop": null, "objects": [{"uuid": "e455ad39c07645e294567be7b9142713"}, {"uuid": "6dfabcd6a7670d5be14bd0ebd97c3274"}, {"uuid": "6cf302fed78f9a25c039398e9a8123b9"}, {"uuid": "92b182865f96cec9fce3b77ac1ca4aa2"}], "camera": {"uuid": "6cf302fed78f9a25c039398e9a8123b9"}, "world": {"uuid": "7d4cb6f31dff5c84e97859ff2275f075"}, "frame_start": 1, "frame_end": 250, "timeline_markers": null, "fps": 24, "audio_volume": 1, "audio_doppler_speed": 343.3, "audio_doppler_factor": 1, "audio_distance_model": "INVERSE_CLAMPED"}], "worlds": [{"name": "World", "uuid": "7d4cb6f31dff5c84e97859ff2275f075", "texture_slots": [], "use_orco_tex_coord": false, "horizon_color": [0.0509, 0.0509, 0.0509], "zenith_color": [0.01, 0.01, 0.01], "use_sky_paper": false, "use_sky_blend": false, "use_sky_real": false, "b4w_use_default_animation": false, "b4w_anim_behavior": "CYCLIC", "use_nodes": false, "uv_vc_key": "", "light_settings": {"use_environment_light": false, "environment_energy": 1, "environment_color": "PLAIN"}, "b4w_sky_settings": {"render_sky": false, "reflexible": true, "reflexible_only": false, "procedural_skydome": false, "use_as_environment_lighting": false, "color": [0.087, 0.255, 0.6], "rayleigh_brightness": 3.3, "mie_brightness": 0.1, "spot_brightness": 20, "scatter_strength": 0.2, "rayleigh_strength": 0.2, "mie_strength": 0.006, "rayleigh_collection_power": 0.35, "mie_collection_power": 0.5, "mie_distribution": 0.4}, "fog_settings": {"use_fog": false, "intensity": 0, "depth": 25, "start": 5, "height": 0, "falloff": "QUADRATIC", "use_custom_color": false, "color": [0.5, 0.5, 0.5]}, "animation_data": null, "node_tree": null}], "node_groups": [], "binaries": [{"binfile": "Sax_player.bin", "int": 0, "float": 488532, "short": 987332, "ushort": 1336380, "uchar": 1336380}], "b4w_export_warnings": [], "b4w_export_errors": []}