{
  "name": "Stage",
  "model_src": "my_project.json",
  "X": 0,
  "Y": 0,
  "turn": 0,
  "Title": "Stage",
  "Comment": "",
  "input_list": [],
  "output_list": [],
  "gear_list": [],
  "children": [
    {
      "id": null,
      "obj": null,
      "name": "CHAIR",
      "Comment": "",
      "input_list": [],
      "output_list": [],
      "gear_list": [
        {
          "Name": "Chair",
          "Category": "Instruments and access",
          "Image": "",
          "Comment": "",
          "Weight": 2,
          "Power_consumption": 0,
          "Weight_round": 0.1,
          "Count_round": 1,
          "Count": 1,
          "Owner": "Rent",
          "Obj_id": 1,
          "obj": null
        }
      ],
      "parent": "",
      "Title": "Chair",
      "selected": false,
      "model_src": "STUL.json",
      "X": 3,
      "Y": -2.8,
      "Z": 0,
      "is_structure": false,
      "Height": 0,
      "turn": 90,
      "Title_to_Source": false,
      "children": [
        {
          "id": null,
          "obj": null,
          "name": "SM81_on_STAND",
          "Comment": "",
          "input_list": [
            {
              "Source": "Violini I",
              "Type": "in",
              "ChName": "SM81",
              "Comment": "",
              "Phantom_power": "On",
              "Channel": 1,
              "Locked": true,
              "Obj_id": 2,
              "obj": null
            }
          ],
          "output_list": [],
          "gear_list": [
            {
              "Name": "Shure SM81",
              "Category": "Microphones and DI",
              "Image": "Shure81.jpg",
              "Comment": "Condenser cardioid instrumental microphone",
              "Weight": 0.2,
              "Power_consumption": 0,
              "Weight_round": 0.1,
              "Count_round": 1,
              "Count": 1,
              "Owner": "Rent",
              "Obj_id": 2,
              "obj": null
            },
            {
              "Name": "Long microphone stand",
              "Category": "Stands",
              "Image": "",
              "Comment": "The long microphone stand with folding tripod base, boom arm, and shock mount",
              "Weight": 2,
              "Power_consumption": 0,
              "Weight_round": 0.1,
              "Count_round": 1,
              "Count": 1,
              "Owner": "Rent",
              "Obj_id": 2,
              "obj": null
            },
            {
              "Name": "Microphone cable",
              "Category": "Wire",
              "Image": "",
              "Comment": "XLR-XLR",
              "Weight": 1,
              "Power_consumption": 0,
              "Weight_round": 0.1,
              "Count_round": 1,
              "Count": 1,
              "Owner": "Rent",
              "Obj_id": 2,
              "obj": null
            }
          ],
          "parent": 1,
          "Title": "Shure sm81",
          "selected": false,
          "model_src": "SM81_on_STAND.json",
          "X": 3.5,
          "Y": -1.98,
          "Z": 0,
          "is_structure": false,
          "Height": 0,
          "turn": 45,
          "Title_to_Source": false,
          "children": [],
          "is_jump": false
        }
      ],
      "is_jump": false
    },
    {
      "id": null,
      "obj": null,
      "name": "CHAIR",
      "Comment": "",
      "input_list": [],
      "output_list": [],
      "gear_list": [
        {
          "Name": "Chair",
          "Category": "Instruments and access",
          "Image": "",
          "Comment": "",
          "Weight": 2,
          "Power_consumption": 0,
          "Weight_round": 0.1,
          "Count_round": 1,
          "Count": 1,
          "Owner": "Rent",
          "Obj_id": 3,
          "obj": null
        }
      ],
      "parent": "",
      "Title": "Chair",
      "selected": false,
      "model_src": "STUL.json",
      "X": 1.2,
      "Y": -2.5,
      "Z": 0,
      "is_structure": false,
      "Height": 0,
      "turn": 45,
      "Title_to_Source": false,
      "children": [],
      "is_jump": false
    },
    {
      "id": null,
      "obj": null,
      "name": "CHAIR",
      "Comment": "",
      "input_list": [],
      "output_list": [],
      "gear_list": [
        {
          "Name": "Chair",
          "Category": "Instruments and access",
          "Image": "",
          "Comment": "",
          "Weight": 2,
          "Power_consumption": 0,
          "Weight_round": 0.1,
          "Count_round": 1,
          "Count": 1,
          "Owner": "Rent",
          "Obj_id": 5,
          "obj": null
        }
      ],
      "parent": "",
      "Title": "Chair",
      "selected": false,
      "model_src": "STUL.json",
      "X": 0.2,
      "Y": -0.8,
      "Z": 0,
      "is_structure": false,
      "Height": 0,
      "turn": 0,
      "Title_to_Source": false,
      "children": [
        {
          "id": null,
          "obj": null,
          "name": "SM81_on_STAND",
          "Comment": "",
          "input_list": [
            {
              "Source": "Viole",
              "Type": "in",
              "ChName": "SM81",
              "Comment": "",
              "Phantom_power": "On",
              "Channel": 3,
              "Locked": true,
              "Obj_id": 6,
              "obj": null
            }
          ],
          "output_list": [],
          "gear_list": [
            {
              "Name": "Shure SM81",
              "Category": "Microphones and DI",
              "Image": "Shure81.jpg",
              "Comment": "Condenser cardioid instrumental microphone",
              "Weight": 0.2,
              "Power_consumption": 0,
              "Weight_round": 0.1,
              "Count_round": 1,
              "Count": 1,
              "Owner": "Rent",
              "Obj_id": 6,
              "obj": null
            },
            {
              "Name": "Long microphone stand",
              "Category": "Stands",
              "Image": "",
              "Comment": "The long microphone stand with folding tripod base, boom arm, and shock mount",
              "Weight": 2,
              "Power_consumption": 0,
              "Weight_round": 0.1,
              "Count_round": 1,
              "Count": 1,
              "Owner": "Rent",
              "Obj_id": 6,
              "obj": null
            },
            {
              "Name": "Microphone cable",
              "Category": "Wire",
              "Image": "",
              "Comment": "XLR-XLR",
              "Weight": 1,
              "Power_consumption": 0,
              "Weight_round": 0.1,
              "Count_round": 1,
              "Count": 1,
              "Owner": "Rent",
              "Obj_id": 6,
              "obj": null
            }
          ],
          "parent": 5,
          "Title": "Shure sm81",
          "selected": false,
          "model_src": "SM81_on_STAND.json",
          "X": 1,
          "Y": -0.8,
          "Z": 0,
          "is_structure": false,
          "Height": 0,
          "turn": 0,
          "Title_to_Source": false,
          "children": [],
          "is_jump": false
        }
      ],
      "is_jump": false
    },
    {
      "id": null,
      "obj": null,
      "name": "CHAIR",
      "Comment": "",
      "input_list": [],
      "output_list": [],
      "gear_list": [
        {
          "Name": "Chair",
          "Category": "Instruments and access",
          "Image": "",
          "Comment": "",
          "Weight": 2,
          "Power_consumption": 0,
          "Weight_round": 0.1,
          "Count_round": 1,
          "Count": 1,
          "Owner": "Rent",
          "Obj_id": 7,
          "obj": null
        }
      ],
      "parent": "",
      "Title": "Chair",
      "selected": false,
      "model_src": "STUL.json",
      "X": 3,
      "Y": -4.1,
      "Z": 0,
      "is_structure": false,
      "Height": 0,
      "turn": 90,
      "Title_to_Source": false,
      "children": [],
      "is_jump": false
    },
    {
      "id": null,
      "obj": null,
      "name": "CHAIR",
      "Comment": "",
      "input_list": [],
      "output_list": [],
      "gear_list": [
        {
          "Name": "Chair",
          "Category": "Instruments and access",
          "Image": "",
          "Comment": "",
          "Weight": 2,
          "Power_consumption": 0,
          "Weight_round": 0.1,
          "Count_round": 1,
          "Count": 1,
          "Owner": "Rent",
          "Obj_id": 9,
          "obj": null
        }
      ],
      "parent": "",
      "Title": "Chair",
      "selected": false,
      "model_src": "STUL.json",
      "X": 3.1,
      "Y": 1.6,
      "Z": 0,
      "is_structure": false,
      "Height": 0,
      "turn": 270,
      "Title_to_Source": false,
      "children": [
        {
          "id": null,
          "obj": null,
          "name": "SM81_on_STAND",
          "Comment": "",
          "input_list": [
            {
              "Source": "Celli",
              "Type": "in",
              "ChName": "SM81",
              "Comment": "",
              "Phantom_power": "On",
              "Channel": 4,
              "Locked": true,
              "Obj_id": 10,
              "obj": null
            }
          ],
          "output_list": [],
          "gear_list": [
            {
              "Name": "Shure SM81",
              "Category": "Microphones and DI",
              "Image": "Shure81.jpg",
              "Comment": "Condenser cardioid instrumental microphone",
              "Weight": 0.2,
              "Power_consumption": 0,
              "Weight_round": 0.1,
              "Count_round": 1,
              "Count": 1,
              "Owner": "Rent",
              "Obj_id": 10,
              "obj": null
            },
            {
              "Name": "Long microphone stand",
              "Category": "Stands",
              "Image": "",
              "Comment": "The long microphone stand with folding tripod base, boom arm, and shock mount",
              "Weight": 2,
              "Power_consumption": 0,
              "Weight_round": 0.1,
              "Count_round": 1,
              "Count": 1,
              "Owner": "Rent",
              "Obj_id": 10,
              "obj": null
            },
            {
              "Name": "Microphone cable",
              "Category": "Wire",
              "Image": "",
              "Comment": "XLR-XLR",
              "Weight": 1,
              "Power_consumption": 0,
              "Weight_round": 0.1,
              "Count_round": 1,
              "Count": 1,
              "Owner": "Rent",
              "Obj_id": 10,
              "obj": null
            }
          ],
          "parent": 9,
          "Title": "Shure sm81",
          "selected": false,
          "model_src": "SM81_on_STAND.json",
          "X": 3.6,
          "Y": 0.9,
          "Z": 0,
          "is_structure": false,
          "Height": 0,
          "turn": 315,
          "Title_to_Source": false,
          "children": [],
          "is_jump": false
        }
      ],
      "is_jump": false
    },
    {
      "id": null,
      "obj": null,
      "name": "CHAIR",
      "Comment": "",
      "input_list": [],
      "output_list": [],
      "gear_list": [
        {
          "Name": "Chair",
          "Category": "Instruments and access",
          "Image": "",
          "Comment": "",
          "Weight": 2,
          "Power_consumption": 0,
          "Weight_round": 0.1,
          "Count_round": 1,
          "Count": 1,
          "Owner": "Rent",
          "Obj_id": 11,
          "obj": null
        }
      ],
      "parent": "",
      "Title": "Chair",
      "selected": false,
      "model_src": "STUL.json",
      "X": 2.3,
      "Y": 1.6,
      "Z": 0,
      "is_structure": false,
      "Height": 0,
      "turn": 270,
      "Title_to_Source": false,
      "children": [],
      "is_jump": false
    },
    {
      "id": null,
      "obj": null,
      "name": "RIZER_PART_2x1_h025",
      "Comment": "",
      "input_list": [],
      "output_list": [],
      "gear_list": [
        {
          "Name": "Rizer part 2x1x0.25",
          "Category": "Stage construction",
          "Image": "",
          "Comment": "",
          "Weight": 20,
          "Power_consumption": 0,
          "Weight_round": 0.1,
          "Count_round": 1,
          "Count": 1,
          "Owner": "Rent",
          "Obj_id": 13,
          "obj": null
        }
      ],
      "parent": "",
      "Title": "Rizer",
      "selected": false,
      "model_src": "RIZER_PART_2x1_h025.json",
      "X": 3.1,
      "Y": -0.5,
      "Z": -8.8,
      "is_structure": true,
      "Height": 0.3,
      "turn": 0,
      "Title_to_Source": false,
      "children": [],
      "is_jump": false
    },
    {
      "id": null,
      "obj": null,
      "name": "CHAIR",
      "Comment": "",
      "input_list": [],
      "output_list": [],
      "gear_list": [
        {
          "Name": "Chair",
          "Category": "Instruments and access",
          "Image": "",
          "Comment": "",
          "Weight": 2,
          "Power_consumption": 0,
          "Weight_round": 0.1,
          "Count_round": 1,
          "Count": 1,
          "Owner": "Rent",
          "Obj_id": 14,
          "obj": null
        }
      ],
      "parent": "",
      "Title": "Chair",
      "selected": false,
      "model_src": "STUL.json",
      "X": 2.9,
      "Y": -5.2,
      "Z": 0,
      "is_structure": false,
      "Height": 0,
      "turn": 90,
      "Title_to_Source": false,
      "children": [],
      "is_jump": false
    },
    {
      "id": null,
      "obj": null,
      "name": "CHAIR",
      "Comment": "",
      "input_list": [],
      "output_list": [],
      "gear_list": [
        {
          "Name": "Chair",
          "Category": "Instruments and access",
          "Image": "",
          "Comment": "",
          "Weight": 2,
          "Power_consumption": 0,
          "Weight_round": 0.1,
          "Count_round": 1,
          "Count": 1,
          "Owner": "Rent",
          "Obj_id": 16,
          "obj": null
        }
      ],
      "parent": "",
      "Title": "Chair",
      "selected": false,
      "model_src": "STUL.json",
      "X": 0.5,
      "Y": -3.3,
      "Z": 0,
      "is_structure": false,
      "Height": 0,
      "turn": 45,
      "Title_to_Source": false,
      "children": [],
      "is_jump": false
    },
    {
      "id": null,
      "obj": null,
      "name": "CHAIR",
      "Comment": "",
      "input_list": [],
      "output_list": [],
      "gear_list": [
        {
          "Name": "Chair",
          "Category": "Instruments and access",
          "Image": "",
          "Comment": "",
          "Weight": 2,
          "Power_consumption": 0,
          "Weight_round": 0.1,
          "Count_round": 1,
          "Count": 1,
          "Owner": "Rent",
          "Obj_id": 18,
          "obj": null
        }
      ],
      "parent": "",
      "Title": "Chair",
      "selected": false,
      "model_src": "STUL.json",
      "X": 0.6,
      "Y": -1.9,
      "Z": 0,
      "is_structure": false,
      "Height": 0,
      "turn": 45,
      "Title_to_Source": false,
      "children": [
        {
          "id": null,
          "obj": null,
          "name": "SM81_on_STAND",
          "Comment": "",
          "input_list": [
            {
              "Source": "Violini II",
              "Type": "in",
              "ChName": "SM81",
              "Comment": "",
              "Phantom_power": "On",
              "Channel": 2,
              "Locked": true,
              "Obj_id": 19,
              "obj": null
            }
          ],
          "output_list": [],
          "gear_list": [
            {
              "Name": "Shure SM81",
              "Category": "Microphones and DI",
              "Image": "Shure81.jpg",
              "Comment": "Condenser cardioid instrumental microphone",
              "Weight": 0.2,
              "Power_consumption": 0,
              "Weight_round": 0.1,
              "Count_round": 1,
              "Count": 1,
              "Owner": "Rent",
              "Obj_id": 19,
              "obj": null
            },
            {
              "Name": "Long microphone stand",
              "Category": "Stands",
              "Image": "",
              "Comment": "The long microphone stand with folding tripod base, boom arm, and shock mount",
              "Weight": 2,
              "Power_consumption": 0,
              "Weight_round": 0.1,
              "Count_round": 1,
              "Count": 1,
              "Owner": "Rent",
              "Obj_id": 19,
              "obj": null
            },
            {
              "Name": "Microphone cable",
              "Category": "Wire",
              "Image": "",
              "Comment": "XLR-XLR",
              "Weight": 1,
              "Power_consumption": 0,
              "Weight_round": 0.1,
              "Count_round": 1,
              "Count": 1,
              "Owner": "Rent",
              "Obj_id": 19,
              "obj": null
            }
          ],
          "parent": 18,
          "Title": "Shure sm81",
          "selected": false,
          "model_src": "SM81_on_STAND.json",
          "X": 1.7,
          "Y": -2,
          "Z": 0,
          "is_structure": false,
          "Height": 0,
          "turn": 0,
          "Title_to_Source": false,
          "children": [],
          "is_jump": false
        }
      ],
      "is_jump": false
    },
    {
      "id": null,
      "obj": null,
      "name": "CHAIR",
      "Comment": "",
      "input_list": [],
      "output_list": [],
      "gear_list": [
        {
          "Name": "Chair",
          "Category": "Instruments and access",
          "Image": "",
          "Comment": "",
          "Weight": 2,
          "Power_consumption": 0,
          "Weight_round": 0.1,
          "Count_round": 1,
          "Count": 1,
          "Owner": "Rent",
          "Obj_id": 20,
          "obj": null
        }
      ],
      "parent": "",
      "Title": "Chair",
      "selected": false,
      "model_src": "STUL.json",
      "X": -0.2,
      "Y": -2.7,
      "Z": 0,
      "is_structure": false,
      "Height": 0,
      "turn": 45,
      "Title_to_Source": false,
      "children": [],
      "is_jump": false
    },
    {
      "id": null,
      "obj": null,
      "name": "CHAIR",
      "Comment": "",
      "input_list": [],
      "output_list": [],
      "gear_list": [
        {
          "Name": "Chair",
          "Category": "Instruments and access",
          "Image": "",
          "Comment": "",
          "Weight": 2,
          "Power_consumption": 0,
          "Weight_round": 0.1,
          "Count_round": 1,
          "Count": 1,
          "Owner": "Rent",
          "Obj_id": 22,
          "obj": null
        }
      ],
      "parent": "",
      "Title": "Chair",
      "selected": false,
      "model_src": "STUL.json",
      "X": 2.1,
      "Y": -5.3,
      "Z": 0,
      "is_structure": false,
      "Height": 0,
      "turn": 90,
      "Title_to_Source": false,
      "children": [],
      "is_jump": false
    },
    {
      "id": null,
      "obj": null,
      "name": "CHAIR",
      "Comment": "",
      "input_list": [],
      "output_list": [],
      "gear_list": [
        {
          "Name": "Chair",
          "Category": "Instruments and access",
          "Image": "",
          "Comment": "",
          "Weight": 2,
          "Power_consumption": 0,
          "Weight_round": 0.1,
          "Count_round": 1,
          "Count": 1,
          "Owner": "Rent",
          "Obj_id": 24,
          "obj": null
        }
      ],
      "parent": "",
      "Title": "Chair",
      "selected": false,
      "model_src": "STUL.json",
      "X": 2.1,
      "Y": -4.2,
      "Z": 0,
      "is_structure": false,
      "Height": 0,
      "turn": 90,
      "Title_to_Source": false,
      "children": [],
      "is_jump": false
    },
    {
      "id": null,
      "obj": null,
      "name": "CHAIR",
      "Comment": "",
      "input_list": [],
      "output_list": [],
      "gear_list": [
        {
          "Name": "Chair",
          "Category": "Instruments and access",
          "Image": "",
          "Comment": "",
          "Weight": 2,
          "Power_consumption": 0,
          "Weight_round": 0.1,
          "Count_round": 1,
          "Count": 1,
          "Owner": "Rent",
          "Obj_id": 26,
          "obj": null
        }
      ],
      "parent": "",
      "Title": "Chair",
      "selected": false,
      "model_src": "STUL.json",
      "X": 2.2,
      "Y": -2.8,
      "Z": 0,
      "is_structure": false,
      "Height": 0,
      "turn": 90,
      "Title_to_Source": false,
      "children": [],
      "is_jump": false
    },
    {
      "id": null,
      "obj": null,
      "name": "MusicStand",
      "Comment": "",
      "input_list": [],
      "output_list": [],
      "gear_list": [],
      "parent": "",
      "Title": "Music Stand",
      "selected": false,
      "model_src": "MusicStand.json",
      "X": 2.7,
      "Y": -2.1,
      "Z": 0,
      "is_structure": false,
      "Height": 0,
      "turn": 90,
      "Title_to_Source": false,
      "children": [],
      "is_jump": false
    },
    {
      "id": null,
      "obj": null,
      "name": "MusicStand",
      "Comment": "",
      "input_list": [],
      "output_list": [],
      "gear_list": [],
      "parent": "",
      "Title": "Music Stand",
      "selected": false,
      "model_src": "MusicStand.json",
      "X": 2.5,
      "Y": -3.4,
      "Z": 0,
      "is_structure": false,
      "Height": 0,
      "turn": 90,
      "Title_to_Source": false,
      "children": [],
      "is_jump": false
    },
    {
      "id": null,
      "obj": null,
      "name": "MusicStand",
      "Comment": "",
      "input_list": [],
      "output_list": [],
      "gear_list": [],
      "parent": "",
      "Title": "Music Stand",
      "selected": false,
      "model_src": "MusicStand.json",
      "X": 2.5,
      "Y": -4.6,
      "Z": 0,
      "is_structure": false,
      "Height": 0,
      "turn": 90,
      "Title_to_Source": false,
      "children": [],
      "is_jump": false
    },
    {
      "id": null,
      "obj": null,
      "name": "MusicStand",
      "Comment": "",
      "input_list": [],
      "output_list": [],
      "gear_list": [],
      "parent": "",
      "Title": "Music Stand",
      "selected": false,
      "model_src": "MusicStand.json",
      "X": 1.5,
      "Y": -1.8,
      "Z": 0,
      "is_structure": false,
      "Height": 0,
      "turn": 45,
      "Title_to_Source": false,
      "children": [],
      "is_jump": false
    },
    {
      "id": null,
      "obj": null,
      "name": "MusicStand",
      "Comment": "",
      "input_list": [],
      "output_list": [],
      "gear_list": [],
      "parent": "",
      "Title": "Music Stand",
      "selected": false,
      "model_src": "MusicStand.json",
      "X": 0.7,
      "Y": -2.5,
      "Z": 0,
      "is_structure": false,
      "Height": 0,
      "turn": 45,
      "Title_to_Source": false,
      "children": [],
      "is_jump": false
    },
    {
      "id": null,
      "obj": null,
      "name": "CHAIR",
      "Comment": "",
      "input_list": [],
      "output_list": [],
      "gear_list": [
        {
          "Name": "Chair",
          "Category": "Instruments and access",
          "Image": "",
          "Comment": "",
          "Weight": 2,
          "Power_consumption": 0,
          "Weight_round": 0.1,
          "Count_round": 1,
          "Count": 1,
          "Owner": "Rent",
          "Obj_id": 33,
          "obj": null
        }
      ],
      "parent": "",
      "Title": "Chair",
      "selected": false,
      "model_src": "STUL.json",
      "X": -1,
      "Y": -0.9,
      "Z": 0,
      "is_structure": false,
      "Height": 0,
      "turn": 0,
      "Title_to_Source": false,
      "children": [],
      "is_jump": false
    },
    {
      "id": null,
      "obj": null,
      "name": "CHAIR",
      "Comment": "",
      "input_list": [],
      "output_list": [],
      "gear_list": [
        {
          "Name": "Chair",
          "Category": "Instruments and access",
          "Image": "",
          "Comment": "",
          "Weight": 2,
          "Power_consumption": 0,
          "Weight_round": 0.1,
          "Count_round": 1,
          "Count": 1,
          "Owner": "Rent",
          "Obj_id": 35,
          "obj": null
        }
      ],
      "parent": "",
      "Title": "Chair",
      "selected": false,
      "model_src": "STUL.json",
      "X": -1,
      "Y": 0,
      "Z": 0,
      "is_structure": false,
      "Height": 0,
      "turn": 0,
      "Title_to_Source": false,
      "children": [],
      "is_jump": false
    },
    {
      "id": null,
      "obj": null,
      "name": "CHAIR",
      "Comment": "",
      "input_list": [],
      "output_list": [],
      "gear_list": [
        {
          "Name": "Chair",
          "Category": "Instruments and access",
          "Image": "",
          "Comment": "",
          "Weight": 2,
          "Power_consumption": 0,
          "Weight_round": 0.1,
          "Count_round": 1,
          "Count": 1,
          "Owner": "Rent",
          "Obj_id": 37,
          "obj": null
        }
      ],
      "parent": "",
      "Title": "Chair",
      "selected": false,
      "model_src": "STUL.json",
      "X": -3,
      "Y": 0.4,
      "Z": 0,
      "is_structure": false,
      "Height": 0,
      "turn": 0,
      "Title_to_Source": false,
      "children": [],
      "is_jump": false
    },
    {
      "id": null,
      "obj": null,
      "name": "MusicStand",
      "Comment": "",
      "input_list": [],
      "output_list": [],
      "gear_list": [],
      "parent": "",
      "Title": "Music Stand",
      "selected": false,
      "model_src": "MusicStand.json",
      "X": -0.2,
      "Y": -0.5,
      "Z": 0,
      "is_structure": false,
      "Height": 0,
      "turn": 0,
      "Title_to_Source": false,
      "children": [],
      "is_jump": false
    },
    {
      "id": null,
      "obj": null,
      "name": "MusicStand",
      "Comment": "",
      "input_list": [],
      "output_list": [],
      "gear_list": [],
      "parent": "",
      "Title": "Music Stand",
      "selected": false,
      "model_src": "MusicStand.json",
      "X": 0.9,
      "Y": -0.4,
      "Z": 0,
      "is_structure": false,
      "Height": 0,
      "turn": 0,
      "Title_to_Source": false,
      "children": [],
      "is_jump": false
    },
    {
      "id": null,
      "obj": null,
      "name": "MusicStand",
      "Comment": "",
      "input_list": [],
      "output_list": [],
      "gear_list": [],
      "parent": "",
      "Title": "Music Stand",
      "selected": false,
      "model_src": "MusicStand.json",
      "X": 2.7,
      "Y": 0.7,
      "Z": 0,
      "is_structure": false,
      "Height": 0,
      "turn": 270,
      "Title_to_Source": false,
      "children": [],
      "is_jump": false
    },
    {
      "id": null,
      "obj": null,
      "name": "CHAIR",
      "Comment": "",
      "input_list": [],
      "output_list": [],
      "gear_list": [
        {
          "Name": "Chair",
          "Category": "Instruments and access",
          "Image": "",
          "Comment": "",
          "Weight": 2,
          "Power_consumption": 0,
          "Weight_round": 0.1,
          "Count_round": 1,
          "Count": 1,
          "Owner": "Rent",
          "Obj_id": 42,
          "obj": null
        }
      ],
      "parent": "",
      "Title": "Chair",
      "selected": false,
      "model_src": "STUL.json",
      "X": 3.1,
      "Y": 2.8,
      "Z": 0,
      "is_structure": false,
      "Height": 0,
      "turn": 270,
      "Title_to_Source": false,
      "children": [],
      "is_jump": false
    },
    {
      "id": null,
      "obj": null,
      "name": "CHAIR",
      "Comment": "",
      "input_list": [],
      "output_list": [],
      "gear_list": [
        {
          "Name": "Chair",
          "Category": "Instruments and access",
          "Image": "",
          "Comment": "",
          "Weight": 2,
          "Power_consumption": 0,
          "Weight_round": 0.1,
          "Count_round": 1,
          "Count": 1,
          "Owner": "Rent",
          "Obj_id": 44,
          "obj": null
        }
      ],
      "parent": "",
      "Title": "Chair",
      "selected": false,
      "model_src": "STUL.json",
      "X": 2.3,
      "Y": 2.7,
      "Z": 0,
      "is_structure": false,
      "Height": 0,
      "turn": 270,
      "Title_to_Source": false,
      "children": [],
      "is_jump": false
    },
    {
      "id": null,
      "obj": null,
      "name": "MusicStand",
      "Comment": "",
      "input_list": [],
      "output_list": [],
      "gear_list": [],
      "parent": "",
      "Title": "Music Stand",
      "selected": false,
      "model_src": "MusicStand.json",
      "X": 2.7,
      "Y": 2.2,
      "Z": 0,
      "is_structure": false,
      "Height": 0,
      "turn": 270,
      "Title_to_Source": false,
      "children": [],
      "is_jump": false
    },
    {
      "id": null,
      "obj": null,
      "name": "CHAIR",
      "Comment": "",
      "input_list": [],
      "output_list": [],
      "gear_list": [
        {
          "Name": "Chair",
          "Category": "Instruments and access",
          "Image": "",
          "Comment": "",
          "Weight": 2,
          "Power_consumption": 0,
          "Weight_round": 0.1,
          "Count_round": 1,
          "Count": 1,
          "Owner": "Rent",
          "Obj_id": 47,
          "obj": null
        }
      ],
      "parent": "",
      "Title": "Chair",
      "selected": false,
      "model_src": "STUL.json",
      "X": -0.1,
      "Y": 1.8,
      "Z": 0,
      "is_structure": false,
      "Height": 0,
      "turn": 315,
      "Title_to_Source": false,
      "children": [],
      "is_jump": false
    },
    {
      "id": null,
      "obj": null,
      "name": "CHAIR",
      "Comment": "",
      "input_list": [],
      "output_list": [],
      "gear_list": [
        {
          "Name": "Chair",
          "Category": "Instruments and access",
          "Image": "",
          "Comment": "",
          "Weight": 2,
          "Power_consumption": 0,
          "Weight_round": 0.1,
          "Count_round": 1,
          "Count": 1,
          "Owner": "Rent",
          "Obj_id": 49,
          "obj": null
        }
      ],
      "parent": "",
      "Title": "Chair",
      "selected": false,
      "model_src": "STUL.json",
      "X": 3.1,
      "Y": 3.9,
      "Z": 0,
      "is_structure": false,
      "Height": 0,
      "turn": 270,
      "Title_to_Source": false,
      "children": [],
      "is_jump": false
    },
    {
      "id": null,
      "obj": null,
      "name": "CHAIR",
      "Comment": "",
      "input_list": [],
      "output_list": [],
      "gear_list": [
        {
          "Name": "Chair",
          "Category": "Instruments and access",
          "Image": "",
          "Comment": "",
          "Weight": 2,
          "Power_consumption": 0,
          "Weight_round": 0.1,
          "Count_round": 1,
          "Count": 1,
          "Owner": "Rent",
          "Obj_id": 51,
          "obj": null
        }
      ],
      "parent": "",
      "Title": "Chair",
      "selected": false,
      "model_src": "STUL.json",
      "X": 2.3,
      "Y": 3.9,
      "Z": 0,
      "is_structure": false,
      "Height": 0,
      "turn": 270,
      "Title_to_Source": false,
      "children": [],
      "is_jump": false
    },
    {
      "id": null,
      "obj": null,
      "name": "MusicStand",
      "Comment": "",
      "input_list": [],
      "output_list": [],
      "gear_list": [],
      "parent": "",
      "Title": "Music Stand",
      "selected": false,
      "model_src": "MusicStand.json",
      "X": 2.8,
      "Y": 3.3,
      "Z": 0,
      "is_structure": false,
      "Height": 0,
      "turn": 270,
      "Title_to_Source": false,
      "children": [],
      "is_jump": false
    },
    {
      "id": null,
      "obj": null,
      "name": "SM81_on_STAND",
      "Comment": "",
      "input_list": [
        {
          "Source": "C-Bass",
          "Type": "in",
          "ChName": "dpa 4061",
          "Comment": "",
          "Phantom_power": "On",
          "Channel": 5,
          "Locked": true,
          "Obj_id": 54,
          "obj": null
        }
      ],
      "output_list": [],
      "gear_list": [
        {
          "Name": "Shure SM81",
          "Category": "Microphones and DI",
          "Image": "Shure81.jpg",
          "Comment": "Condenser cardioid instrumental microphone",
          "Weight": 0.2,
          "Power_consumption": 0,
          "Weight_round": 0.1,
          "Count_round": 1,
          "Count": 1,
          "Owner": "Rent",
          "Obj_id": 54,
          "obj": null
        },
        {
          "Name": "Long microphone stand",
          "Category": "Stands",
          "Image": "",
          "Comment": "The long microphone stand with folding tripod base, boom arm, and shock mount",
          "Weight": 2,
          "Power_consumption": 0,
          "Weight_round": 0.1,
          "Count_round": 1,
          "Count": 1,
          "Owner": "Rent",
          "Obj_id": 54,
          "obj": null
        },
        {
          "Name": "Microphone cable",
          "Category": "Wire",
          "Image": "",
          "Comment": "XLR-XLR",
          "Weight": 1,
          "Power_consumption": 0,
          "Weight_round": 0.1,
          "Count_round": 1,
          "Count": 1,
          "Owner": "Rent",
          "Obj_id": 54,
          "obj": null
        }
      ],
      "parent": "",
      "Title": "Shure sm81",
      "selected": false,
      "model_src": "SM81_on_STAND.json",
      "X": 0.7,
      "Y": 1.2,
      "Z": 0,
      "is_structure": false,
      "Height": 0,
      "turn": 315,
      "Title_to_Source": false,
      "children": [],
      "is_jump": false
    }
  ]
}