{"b4w_format_version": "6.03", "b4w_filepath_blend": "../blender_resized/gtr_stands.blend", "actions": [], "images": [], "textures": [], "materials": [{"use_orco_tex_coord": false, "name": ",Black Nero", "use_nodes": false, "diffuse_color": [0.0078, 0.0078, 0.0078], "diffuse_shader": "LAMBERT", "roughness": 0.5, "diffuse_fresnel": 0.1, "diffuse_fresnel_factor": 0.5, "darkness": 1, "diffuse_toon_size": 0.5, "diffuse_toon_smooth": 0.1, "diffuse_intensity": 0.8, "alpha": 1, "specular_alpha": 1, "raytrace_mirror": {"reflect_factor": 0, "fresnel": 0, "fresnel_factor": 1.25}, "specular_color": [0.0863, 0.0863, 0.0863], "specular_intensity": 0.5, "specular_shader": "COOKTORR", "specular_hardness": 50, "specular_ior": 4, "specular_slope": 0.1, "specular_toon_size": 0.5, "specular_toon_smooth": 0.1, "emit": 0, "ambient": 1, "use_vertex_color_paint": false, "b4w_water": false, "b4w_water_shore_smoothing": true, "b4w_water_absorb_factor": 6, "b4w_water_dynamic": false, "b4w_waves_height": 1, "b4w_waves_length": 10, "b4w_generated_mesh": false, "b4w_water_num_cascads": 5, "b4w_water_subdivs": 64, "b4w_water_detailed_dist": 1000, "b4w_water_fog_color": [0.4, 0.6, 0.7], "b4w_water_fog_density": 0.06, "b4w_foam_factor": 0.5, "b4w_shallow_water_col": [0, 0.8, 0.3], "b4w_shore_water_col": [0, 0.9, 0.2], "b4w_shallow_water_col_fac": 1, "b4w_shore_water_col_fac": 0.5, "b4w_water_dst_noise_scale0": 0.05, "b4w_water_dst_noise_scale1": 0.03, "b4w_water_dst_noise_freq0": 1.3, "b4w_water_dst_noise_freq1": 1, "b4w_water_dir_min_shore_fac": 0.4, "b4w_water_dir_freq": 0.5, "b4w_water_dir_noise_scale": 0.05, "b4w_water_dir_noise_freq": 0.07, "b4w_water_dir_min_noise_fac": 0.5, "b4w_water_dst_min_fac": 0.2, "b4w_water_waves_hor_fac": 5, "b4w_water_sss_strength": 1, "b4w_water_sss_width": 0.45, "b4w_water_norm_uv_velocity": 0.05, "b4w_water_enable_caust": false, "b4w_water_caust_scale": 0.25, "b4w_water_caust_brightness": 0.5, "b4w_terrain": false, "b4w_dynamic_grass_size": "", "b4w_dynamic_grass_color": "", "b4w_do_not_render": false, "b4w_lens_flares": false, "b4w_collision": false, "b4w_use_ghost": false, "b4w_collision_id": "", "b4w_collision_margin": 0.03999999910593033, "b4w_collision_group": 128, "b4w_collision_mask": 65407, "b4w_double_sided_lighting": false, "b4w_wettable": false, "b4w_refractive": false, "b4w_refr_bump": 0.0010000000474974513, "b4w_render_above_all": false, "physics": {"friction": 0.5, "elasticity": 0}, "type": "SURFACE", "b4w_halo_sky_stars": false, "b4w_halo_stars_blend_height": 10.0, "b4w_halo_stars_min_height": 0.0, "halo": {"hardness": 50, "size": 0.5, "b4w_halo_rings_color": [0, 0, 0], "b4w_halo_lines_color": [0.0863, 0.0863, 0.0863], "ring_count": 0, "line_count": 0, "star_tip_count": 0}, "use_transparency": false, "use_shadeless": false, "use_tangent_shading": false, "pass_index": 0, "offset_z": 0, "game_settings": {"alpha_blend": "OPAQUE", "use_backface_culling": true}, "uv_vc_key": "", "node_tree": null, "texture_slots": [], "uuid": "011edc86f9f5fafb30b44590eddf5d02", "source_uuid": "011edc86f9f5fafb30b44590eddf5d02"}, {"use_orco_tex_coord": false, "name": "glossy", "use_nodes": false, "diffuse_color": [0.4196, 0.4549, 0.5804], "diffuse_shader": "LAMBERT", "roughness": 0.5, "diffuse_fresnel": 0.1, "diffuse_fresnel_factor": 0.5, "darkness": 1, "diffuse_toon_size": 0.5, "diffuse_toon_smooth": 0.1, "diffuse_intensity": 0.8, "alpha": 1, "specular_alpha": 1, "raytrace_mirror": {"reflect_factor": 0, "fresnel": 0, "fresnel_factor": 1.25}, "specular_color": [0.1529, 0.1529, 0.1529], "specular_intensity": 0.5, "specular_shader": "COOKTORR", "specular_hardness": 50, "specular_ior": 4, "specular_slope": 0.1, "specular_toon_size": 0.5, "specular_toon_smooth": 0.1, "emit": 0, "ambient": 1, "use_vertex_color_paint": false, "b4w_water": false, "b4w_water_shore_smoothing": true, "b4w_water_absorb_factor": 6, "b4w_water_dynamic": false, "b4w_waves_height": 1, "b4w_waves_length": 10, "b4w_generated_mesh": false, "b4w_water_num_cascads": 5, "b4w_water_subdivs": 64, "b4w_water_detailed_dist": 1000, "b4w_water_fog_color": [0.4, 0.6, 0.7], "b4w_water_fog_density": 0.06, "b4w_foam_factor": 0.5, "b4w_shallow_water_col": [0, 0.8, 0.3], "b4w_shore_water_col": [0, 0.9, 0.2], "b4w_shallow_water_col_fac": 1, "b4w_shore_water_col_fac": 0.5, "b4w_water_dst_noise_scale0": 0.05, "b4w_water_dst_noise_scale1": 0.03, "b4w_water_dst_noise_freq0": 1.3, "b4w_water_dst_noise_freq1": 1, "b4w_water_dir_min_shore_fac": 0.4, "b4w_water_dir_freq": 0.5, "b4w_water_dir_noise_scale": 0.05, "b4w_water_dir_noise_freq": 0.07, "b4w_water_dir_min_noise_fac": 0.5, "b4w_water_dst_min_fac": 0.2, "b4w_water_waves_hor_fac": 5, "b4w_water_sss_strength": 1, "b4w_water_sss_width": 0.45, "b4w_water_norm_uv_velocity": 0.05, "b4w_water_enable_caust": false, "b4w_water_caust_scale": 0.25, "b4w_water_caust_brightness": 0.5, "b4w_terrain": false, "b4w_dynamic_grass_size": "", "b4w_dynamic_grass_color": "", "b4w_do_not_render": false, "b4w_lens_flares": false, "b4w_collision": false, "b4w_use_ghost": false, "b4w_collision_id": "", "b4w_collision_margin": 0.03999999910593033, "b4w_collision_group": 128, "b4w_collision_mask": 65407, "b4w_double_sided_lighting": false, "b4w_wettable": false, "b4w_refractive": false, "b4w_refr_bump": 0.0010000000474974513, "b4w_render_above_all": false, "physics": {"friction": 0.5, "elasticity": 0}, "type": "SURFACE", "b4w_halo_sky_stars": false, "b4w_halo_stars_blend_height": 10.0, "b4w_halo_stars_min_height": 0.0, "halo": {"hardness": 50, "size": 0.5, "b4w_halo_rings_color": [0, 0, 0], "b4w_halo_lines_color": [0.1529, 0.1529, 0.1529], "ring_count": 0, "line_count": 0, "star_tip_count": 0}, "use_transparency": false, "use_shadeless": false, "use_tangent_shading": false, "pass_index": 0, "offset_z": 0, "game_settings": {"alpha_blend": "OPAQUE", "use_backface_culling": true}, "uv_vc_key": "", "node_tree": null, "texture_slots": [], "uuid": "5d55accfa6733bc27e0f6c9d8d6d9cd9", "source_uuid": "5d55accfa6733bc27e0f6c9d8d6d9cd9"}], "meshes": [{"name": "objg_stand.001", "uuid": "72fbfe458be1472129b2b380fa67184f", "materials": [{"uuid": "011edc86f9f5fafb30b44590eddf5d02"}, {"uuid": "5d55accfa6733bc27e0f6c9d8d6d9cd9"}], "b4w_vertex_anim": [], "vertex_groups": [], "uv_textures": [], "active_vcol_name": "", "active_uv_name": "", "submeshes": [{"boundings": {"bb": {"max_x": 0.6448, "max_y": 0.46382, "max_z": 1.94145, "min_x": -0.54539, "min_y": -0.46913, "min_z": 0.01793}, "be_ax": [1.03049, 0.78491, 1.69118], "be_cen": [0.05135, -0.0188, 0.96973], "rbb": {"rbb_c": [0.05392789840698242, -0.03300156071782112, 0.973435640335083], "rbb_s": [0.5951653718948364, 0.4533296823501587, 0.976749062538147]}, "caxis_x": [0.9999890923500061, 0.00021476185065694153, -0.004666839726269245], "caxis_y": [0.0, 0.9989427924156189, 0.04597003757953644], "caxis_z": [0.004671778995543718, -0.045969534665346146, 0.998931884765625]}, "base_length": 9699, "indices": [0, 11967], "position": [0, 29097], "texcoord": [0, 0], "shade_tangs": [0, 0], "normal": [0, 29097], "tangent": [0, 0], "group": [0, 0], "color": [0, 0], "vertex_colors": [], "uv_layers": []}, {"boundings": {"bb": {"max_x": 0.6487, "max_y": 0.46913, "max_z": 0.12178, "min_x": -0.6487, "min_y": -0.29804, "min_z": 0.00194}, "be_ax": [1.11872, 0.67464, 0.10409], "be_cen": [-0.00541, 0.08271, 0.06149], "rbb": {"rbb_c": [0.008437477052211761, 0.07771481573581696, 0.06146891415119171], "rbb_s": [0.6484850645065308, 0.3910653591156006, 0.060338981449604034]}, "caxis_x": [0.999660074710846, -0.026010936126112938, 0.0017999910051003098], "caxis_y": [0.02601097710430622, 0.9996616840362549, 0.0], "caxis_z": [-0.0017993820365518332, 4.6819524868624285e-05, 0.9999983906745911]}, "base_length": 919, "indices": [11967, 1323], "position": [29097, 2757], "texcoord": [0, 0], "shade_tangs": [0, 0], "normal": [29097, 2757], "tangent": [0, 0], "group": [0, 0], "color": [0, 0], "vertex_colors": [], "uv_layers": []}], "b4w_shape_keys": [], "b4w_boundings": {"bb": {"max_x": 0.6487, "max_y": 0.46913, "max_z": 1.94145, "min_x": -0.6487, "min_y": -0.46913, "min_z": 0.00194}, "be_ax": [1.12363, 0.79361, 1.70133], "be_cen": [0, -0.01352, 0.96135], "bs_rad": 1.11692, "bc_rad": 0.69217, "bs_cen": [-0.03171, -0.03085, 0.88409], "bc_cen": [-0.00052, -0.01524, 0.9717], "bb_src": {"max_x": 0.6487, "max_y": 0.46913, "max_z": 1.94145, "min_x": -0.6487, "min_y": -0.46913, "min_z": 0.00194}, "rbb": {"rbb_c": [0.0, -0.025619463995099068, 0.9669685363769531], "rbb_s": [0.6486999988555908, 0.4581734538078308, 0.982221782207489]}, "caxis_x": [1.0, 0.0, 0.0], "caxis_y": [0.0, 0.999208390712738, 0.03978189453482628], "caxis_z": [0.0, -0.03978189453482628, 0.999208390712738]}, "is_boundings_overridden": false}], "armatures": [], "cameras": [{"name": "Camera", "uuid": "1f1897c89678e7c834eeb53cdcdc4308", "type": "PERSP", "angle": 0.857556, "angle_y": 0.50338, "sensor_fit": "AUTO", "ortho_scale": 7.314, "clip_start": 0.1, "clip_end": 100, "dof_distance": 0, "b4w_dof_front_start": 1, "b4w_dof_front_end": 5, "b4w_dof_rear_start": 1, "b4w_dof_rear_end": 5, "b4w_dof_power": 2, "b4w_dof_bokeh": false, "b4w_dof_bokeh_intensity": 0.3, "b4w_dof_foreground_blur": false, "b4w_move_style": "TARGET", "b4w_hover_zero_level": 0.0, "b4w_trans_velocity": 1, "b4w_rot_velocity": 1, "b4w_zoom_velocity": 0.1, "b4w_use_target_distance_limits": false, "b4w_distance_min": 1, "b4w_distance_max": 10, "b4w_use_horizontal_clamping": false, "b4w_rotation_left_limit": -0.7853981852531433, "b4w_rotation_right_limit": 0.7853981852531433, "b4w_horizontal_clamping_type": "LOCAL", "b4w_use_vertical_clamping": false, "b4w_rotation_down_limit": -0.7853981852531433, "b4w_rotation_up_limit": 0.7853981852531433, "b4w_vertical_clamping_type": "LOCAL", "b4w_horizontal_translation_min": -10, "b4w_horizontal_translation_max": 10, "b4w_vertical_translation_min": -10, "b4w_vertical_translation_max": 10, "b4w_use_zooming": false, "b4w_hover_angle_min": 0.0, "b4w_hover_angle_max": 1.5707963705062866, "b4w_enable_hover_hor_rotation": true, "b4w_use_panning": true, "b4w_use_pivot_limits": false, "b4w_pivot_z_min": 0.0, "b4w_pivot_z_max": 10.0, "b4w_target": [0, 0, 0], "dof_object": null}], "curves": [], "lamps": [{"animation_data": null, "name": "Lamp", "uuid": "befb959028c845a96da52963597a11d6", "type": "POINT", "energy": 1, "distance": 30, "use_diffuse": true, "use_specular": true, "falloff_type": "INVERSE_SQUARE", "clip_start": 1.0007989406585693, "clip_end": 30.00200080871582, "use_sphere": false, "spot_size": null, "spot_blend": null, "b4w_generate_shadows": true, "b4w_dynamic_intensity": false, "color": [1, 1, 1]}], "sounds": [], "speakers": [], "particles": [], "objects": [{"name": "gtr_stand_ns", "uuid": "3b75aa452e9b447494f69d4d70c761c5", "type": "MESH", "body_text": null, "data": {"uuid": "72fbfe458be1472129b2b380fa67184f"}, "proxy": null, "dupli_group": null, "parent": null, "b4w_viewport_alignment": null, "pinverse_tsr": null, "parent_type": "OBJECT", "parent_bone": "", "b4w_cluster_data": {"cluster_id": -1, "cluster_center": null, "cluster_radius": 0}, "modifiers": [], "constraints": [], "particle_systems": [], "animation_data": null, "b4w_do_not_batch": true, "b4w_dynamic_geometry": false, "b4w_do_not_cull": false, "b4w_disable_fogging": false, "b4w_do_not_render": false, "b4w_hidden_on_load": false, "b4w_hide_chldr_on_load": false, "b4w_shadow_cast": false, "b4w_shadow_receive": false, "b4w_reflexible": false, "b4w_reflexible_only": false, "b4w_reflective": false, "b4w_reflection_type": "PLANE", "b4w_caustics": false, "b4w_wind_bending": false, "b4w_wind_bending_angle": 10, "b4w_wind_bending_freq": 0.25, "b4w_detail_bending_amp": 0.1, "b4w_detail_bending_freq": 1, "b4w_branch_bending_amp": 0.3, "b4w_main_bend_stiffness_col": "", "b4w_detail_bend_colors": {"leaves_stiffness_col": "", "leaves_phase_col": "", "overall_stiffness_col": ""}, "lod_levels": [], "b4w_proxy_inherit_anim": true, "b4w_selectable": true, "b4w_outlining": true, "b4w_billboard": false, "b4w_pres_glob_orientation": false, "b4w_billboard_geometry": "SPHERICAL", "b4w_outline_settings": {"outline_duration": 1, "outline_period": 1, "outline_relapses": 0}, "b4w_outline_on_select": false, "b4w_use_default_animation": false, "b4w_anim_behavior": "CYCLIC", "b4w_animation_mixing": false, "b4w_shadow_cast_only": false, "b4w_collision": true, "b4w_collision_id": "MUSICOBJ", "b4w_vehicle": false, "b4w_vehicle_settings": null, "b4w_character": false, "b4w_character_settings": null, "b4w_floating": false, "b4w_floating_settings": null, "pose": null, "field": null, "b4w_correct_bounding_offset": "AUTO", "game": {"physics_type": "STATIC", "use_ghost": true, "use_sleep": false, "mass": 1, "velocity_min": 0, "velocity_max": 0, "damping": 0.04, "rotation_damping": 0.1, "lock_location_x": false, "lock_location_y": false, "lock_location_z": false, "lock_rotation_x": false, "lock_rotation_y": false, "lock_rotation_z": false, "collision_margin": 0.03999999910593033, "collision_group": 1, "collision_mask": 65535, "use_collision_bounds": true, "collision_bounds_type": "BOX", "use_collision_compound": false}, "pass_index": 0, "location": [0, 0, 0], "rotation_quaternion": [0.70711, 0, 0, 0.70711], "scale": [0.4, 0.4, 0.4], "b4w_object_tags": null, "b4w_custom_prop": null, "b4w_anchor": null}, {"name": "Empty", "uuid": "b87a046c74fc65be81621d86a77c5ac3", "type": "EMPTY", "body_text": null, "data": "", "proxy": null, "dupli_group": null, "parent": {"uuid": "3b75aa452e9b447494f69d4d70c761c5"}, "b4w_viewport_alignment": null, "parent_type": "OBJECT", "parent_bone": "", "b4w_cluster_data": {"cluster_id": -1, "cluster_center": null, "cluster_radius": 0}, "modifiers": [], "constraints": [], "particle_systems": [], "animation_data": null, "b4w_do_not_batch": false, "b4w_dynamic_geometry": false, "b4w_do_not_cull": false, "b4w_disable_fogging": false, "b4w_do_not_render": false, "b4w_hidden_on_load": false, "b4w_hide_chldr_on_load": false, "b4w_shadow_cast": false, "b4w_shadow_receive": false, "b4w_reflexible": false, "b4w_reflexible_only": false, "b4w_reflective": false, "b4w_reflection_type": "PLANE", "b4w_caustics": false, "b4w_wind_bending": false, "b4w_wind_bending_angle": 10, "b4w_wind_bending_freq": 0.25, "b4w_detail_bending_amp": 0.1, "b4w_detail_bending_freq": 1, "b4w_branch_bending_amp": 0.3, "b4w_main_bend_stiffness_col": "", "b4w_detail_bend_colors": {"leaves_stiffness_col": "", "leaves_phase_col": "", "overall_stiffness_col": ""}, "lod_levels": [], "b4w_proxy_inherit_anim": true, "b4w_selectable": false, "b4w_outlining": false, "b4w_billboard": false, "b4w_pres_glob_orientation": false, "b4w_billboard_geometry": "SPHERICAL", "b4w_outline_settings": {"outline_duration": 1, "outline_period": 1, "outline_relapses": 0}, "b4w_outline_on_select": false, "b4w_use_default_animation": false, "b4w_anim_behavior": "CYCLIC", "b4w_animation_mixing": false, "b4w_shadow_cast_only": false, "b4w_collision": false, "b4w_collision_id": "", "b4w_vehicle": false, "b4w_vehicle_settings": null, "b4w_character": false, "b4w_character_settings": null, "b4w_floating": false, "b4w_floating_settings": null, "pose": null, "field": null, "b4w_correct_bounding_offset": "AUTO", "game": {"physics_type": "NO_COLLISION", "use_ghost": false, "use_sleep": false, "mass": 1, "velocity_min": 0, "velocity_max": 0, "damping": 0.04, "rotation_damping": 0.1, "lock_location_x": false, "lock_location_y": false, "lock_location_z": false, "lock_rotation_x": false, "lock_rotation_y": false, "lock_rotation_z": false, "collision_margin": 0.03999999910593033, "collision_group": 1, "collision_mask": 65535, "use_collision_bounds": false, "collision_bounds_type": "BOX", "use_collision_compound": false}, "pass_index": 0, "pinverse_tsr": [0, 0, 0, 1, 0, 0, 0, 1], "location": [0.02886, -0.00721, 0.08199], "rotation_quaternion": [1, 0, 0, 0], "scale": [1, 1, 1], "b4w_object_tags": null, "b4w_custom_prop": null, "b4w_anchor": {"type": "GENERIC", "detect_visibility": false, "element_id": "", "max_width": 250}}, {"name": "Lamp", "uuid": "4f99769506456e5eb4592b5c8ed597ff", "type": "LAMP", "body_text": null, "data": {"uuid": "befb959028c845a96da52963597a11d6"}, "proxy": null, "dupli_group": null, "parent": null, "b4w_viewport_alignment": null, "pinverse_tsr": null, "parent_type": "OBJECT", "parent_bone": "", "b4w_cluster_data": {"cluster_id": -1, "cluster_center": null, "cluster_radius": 0}, "modifiers": [], "constraints": [], "particle_systems": [], "animation_data": null, "b4w_do_not_batch": false, "b4w_dynamic_geometry": false, "b4w_do_not_cull": false, "b4w_disable_fogging": false, "b4w_do_not_render": false, "b4w_hidden_on_load": false, "b4w_hide_chldr_on_load": false, "b4w_shadow_cast": false, "b4w_shadow_receive": false, "b4w_reflexible": false, "b4w_reflexible_only": false, "b4w_reflective": false, "b4w_reflection_type": "PLANE", "b4w_caustics": false, "b4w_wind_bending": false, "b4w_wind_bending_angle": 10, "b4w_wind_bending_freq": 0.25, "b4w_detail_bending_amp": 0.1, "b4w_detail_bending_freq": 1, "b4w_branch_bending_amp": 0.3, "b4w_main_bend_stiffness_col": "", "b4w_detail_bend_colors": {"leaves_stiffness_col": "", "leaves_phase_col": "", "overall_stiffness_col": ""}, "lod_levels": [], "b4w_proxy_inherit_anim": true, "b4w_selectable": false, "b4w_outlining": false, "b4w_billboard": false, "b4w_pres_glob_orientation": false, "b4w_billboard_geometry": "SPHERICAL", "b4w_outline_settings": {"outline_duration": 1, "outline_period": 1, "outline_relapses": 0}, "b4w_outline_on_select": false, "b4w_use_default_animation": false, "b4w_anim_behavior": "CYCLIC", "b4w_animation_mixing": false, "b4w_shadow_cast_only": false, "b4w_collision": false, "b4w_collision_id": "", "b4w_vehicle": false, "b4w_vehicle_settings": null, "b4w_character": false, "b4w_character_settings": null, "b4w_floating": false, "b4w_floating_settings": null, "pose": null, "field": null, "b4w_correct_bounding_offset": "AUTO", "game": {"physics_type": "STATIC", "use_ghost": false, "use_sleep": false, "mass": 1, "velocity_min": 0, "velocity_max": 0, "damping": 0.025, "rotation_damping": 0.159, "lock_location_x": false, "lock_location_y": false, "lock_location_z": false, "lock_rotation_x": false, "lock_rotation_y": false, "lock_rotation_z": false, "collision_margin": 0.05999999865889549, "collision_group": 1, "collision_mask": 255, "use_collision_bounds": false, "collision_bounds_type": "BOX", "use_collision_compound": false}, "pass_index": 0, "location": [3.35012, -2.76068, 2.28144], "rotation_quaternion": [0.57095, 0.16908, 0.27217, 0.75588], "scale": [1, 1, 1], "b4w_object_tags": null, "b4w_custom_prop": null, "b4w_anchor": null}, {"name": "Camera", "uuid": "e5ce7c3c4fa1cb7c197296c2970af2bf", "type": "CAMERA", "body_text": null, "data": {"uuid": "1f1897c89678e7c834eeb53cdcdc4308"}, "proxy": null, "dupli_group": null, "parent": null, "b4w_viewport_alignment": null, "pinverse_tsr": null, "parent_type": "OBJECT", "parent_bone": "", "b4w_cluster_data": {"cluster_id": -1, "cluster_center": null, "cluster_radius": 0}, "modifiers": [], "constraints": [], "particle_systems": [], "animation_data": null, "b4w_do_not_batch": false, "b4w_dynamic_geometry": false, "b4w_do_not_cull": false, "b4w_disable_fogging": false, "b4w_do_not_render": false, "b4w_hidden_on_load": false, "b4w_hide_chldr_on_load": false, "b4w_shadow_cast": false, "b4w_shadow_receive": false, "b4w_reflexible": false, "b4w_reflexible_only": false, "b4w_reflective": false, "b4w_reflection_type": "PLANE", "b4w_caustics": false, "b4w_wind_bending": false, "b4w_wind_bending_angle": 10, "b4w_wind_bending_freq": 0.25, "b4w_detail_bending_amp": 0.1, "b4w_detail_bending_freq": 1, "b4w_branch_bending_amp": 0.3, "b4w_main_bend_stiffness_col": "", "b4w_detail_bend_colors": {"leaves_stiffness_col": "", "leaves_phase_col": "", "overall_stiffness_col": ""}, "lod_levels": [], "b4w_proxy_inherit_anim": true, "b4w_selectable": false, "b4w_outlining": false, "b4w_billboard": false, "b4w_pres_glob_orientation": false, "b4w_billboard_geometry": "SPHERICAL", "b4w_outline_settings": {"outline_duration": 1, "outline_period": 1, "outline_relapses": 0}, "b4w_outline_on_select": false, "b4w_use_default_animation": false, "b4w_anim_behavior": "CYCLIC", "b4w_animation_mixing": false, "b4w_shadow_cast_only": false, "b4w_collision": false, "b4w_collision_id": "", "b4w_vehicle": false, "b4w_vehicle_settings": null, "b4w_character": false, "b4w_character_settings": null, "b4w_floating": false, "b4w_floating_settings": null, "pose": null, "field": null, "b4w_correct_bounding_offset": "AUTO", "game": {"physics_type": "STATIC", "use_ghost": false, "use_sleep": false, "mass": 1, "velocity_min": 0, "velocity_max": 0, "damping": 0.566, "rotation_damping": 0.626, "lock_location_x": false, "lock_location_y": false, "lock_location_z": false, "lock_rotation_x": false, "lock_rotation_y": false, "lock_rotation_z": false, "collision_margin": 0.05999999865889549, "collision_group": 1, "collision_mask": 255, "use_collision_bounds": false, "collision_bounds_type": "BOX", "use_collision_compound": false}, "pass_index": 0, "location": [4.88682, 1.38355, 1.86518], "rotation_quaternion": [0.42688, 0.33684, 0.51986, 0.65883], "scale": [1, 1, 1], "b4w_object_tags": null, "b4w_custom_prop": null, "b4w_anchor": null}], "groups": [], "scenes": [{"name": "Scene", "uuid": "6eb07b7179d355b810af719307b7934a", "b4w_use_nla": false, "b4w_nla_cyclic": false, "b4w_logic_nodes": [], "b4w_use_logic_editor": false, "b4w_enable_dynamic_compressor": false, "b4w_dynamic_compressor_settings": {"threshold": -24, "knee": 30, "ratio": 12, "attack": 0.003, "release": 0.25}, "b4w_shadow_settings": {"csm_resolution": 2048, "blur_samples": "16x", "soft_shadows": true, "self_shadow_polygon_offset": 1, "self_shadow_normal_offset": 0.01, "b4w_enable_csm": false, "csm_num": 1, "csm_first_cascade_border": 10, "first_cascade_blur_radius": 3, "csm_last_cascade_border": 100, "last_cascade_blur_radius": 1.5, "fade_last_cascade": true, "blend_between_cascades": true}, "b4w_god_rays_settings": {"intensity": 0.7, "max_ray_length": 1, "steps_per_pass": 10}, "b4w_ssao_settings": {"radius_increase": 3, "hemisphere": false, "blur_depth": false, "blur_discard_value": 1, "influence": 0.7, "dist_factor": 0, "samples": 16}, "b4w_color_correction_settings": {"brightness": 0, "contrast": 0, "exposure": 1, "saturation": 1}, "b4w_bloom_settings": {"key": 1, "blur": 4, "edge_lum": 1, "adaptive": true, "average_luminance": 0.5}, "b4w_motion_blur_settings": {"motion_blur_factor": 0.01, "motion_blur_decay_threshold": 0.01}, "b4w_glow_settings": {"render_glow_over_blend": false, "small_glow_mask_coeff": 2, "large_glow_mask_coeff": 2, "small_glow_mask_width": 2, "large_glow_mask_width": 6}, "b4w_outline_color": [1, 1, 1], "b4w_outline_factor": 1, "b4w_enable_physics": "AUTO", "b4w_render_shadows": "AUTO", "b4w_render_reflections": "ON", "b4w_reflection_quality": "MEDIUM", "b4w_render_refractions": "AUTO", "b4w_render_dynamic_grass": "AUTO", "b4w_enable_god_rays": false, "b4w_enable_glow_materials": "AUTO", "b4w_enable_ssao": false, "b4w_batch_grid_size": 0, "b4w_anisotropic_filtering": "OFF", "b4w_enable_bloom": false, "b4w_enable_motion_blur": false, "b4w_enable_color_correction": false, "b4w_antialiasing_quality": "MEDIUM", "b4w_enable_object_selection": "AUTO", "b4w_enable_outlining": "AUTO", "b4w_enable_anchors_visibility": "AUTO", "b4w_lod_smooth_type": "NON-OPAQUE", "b4w_lod_hyst_interval": 4.0, "b4w_tags": null, "b4w_custom_prop": null, "objects": [{"uuid": "3b75aa452e9b447494f69d4d70c761c5"}, {"uuid": "b87a046c74fc65be81621d86a77c5ac3"}, {"uuid": "4f99769506456e5eb4592b5c8ed597ff"}, {"uuid": "e5ce7c3c4fa1cb7c197296c2970af2bf"}], "camera": {"uuid": "e5ce7c3c4fa1cb7c197296c2970af2bf"}, "world": {"uuid": "87dc5102256be4620ea310573d7af92c"}, "frame_start": 1, "frame_end": 250, "timeline_markers": null, "fps": 24, "audio_volume": 1, "audio_doppler_speed": 343.3, "audio_doppler_factor": 1, "audio_distance_model": "INVERSE_CLAMPED"}], "worlds": [{"name": "World", "uuid": "87dc5102256be4620ea310573d7af92c", "texture_slots": [], "use_orco_tex_coord": false, "horizon_color": [0.0509, 0.0509, 0.0509], "zenith_color": [0.01, 0.01, 0.01], "use_sky_paper": false, "use_sky_blend": false, "use_sky_real": false, "b4w_use_default_animation": false, "b4w_anim_behavior": "CYCLIC", "use_nodes": false, "uv_vc_key": "", "light_settings": {"use_environment_light": false, "environment_energy": 1, "environment_color": "PLAIN"}, "b4w_sky_settings": {"render_sky": false, "reflexible": true, "reflexible_only": false, "procedural_skydome": false, "use_as_environment_lighting": false, "color": [0.087, 0.255, 0.6], "rayleigh_brightness": 3.3, "mie_brightness": 0.1, "spot_brightness": 20, "scatter_strength": 0.2, "rayleigh_strength": 0.2, "mie_strength": 0.006, "rayleigh_collection_power": 0.35, "mie_collection_power": 0.5, "mie_distribution": 0.4}, "fog_settings": {"use_fog": false, "intensity": 0, "depth": 25, "start": 5, "height": 0, "falloff": "QUADRATIC", "use_custom_color": false, "color": [0.5, 0.5, 0.5]}, "animation_data": null, "node_tree": null}], "node_groups": [], "binaries": [{"binfile": "gtr_stand_ns.bin", "int": 0, "float": 53160, "short": 180576, "ushort": 244284, "uchar": 244284}], "b4w_export_warnings": [], "b4w_export_errors": [{"text": "IMAGE texture type is not supported for world \"World\".", "type": "ALL"}]}